{
  "data": [
    {
      "hoverinfo": "none",
      "line": {
        "color": "#9966cc",
        "shape": "linear",
        "width": 1.6923076923076923
      },
      "mode": "lines",
      "textposition": "middle center",
      "type": "scatter",
      "x": [
        0.700297,
        -0.112176
      ],
      "y": [
        0.633747,
        0.912221
      ]
    },
    {
      "hoverinfo": "none",
      "line": {
        "color": "#9966cc",
        "shape": "linear",
        "width": 3.076923076923077
      },
      "mode": "lines",
      "textposition": "middle center",
      "type": "scatter",
      "x": [
        0.025478,
        0.443082
      ],
      "y": [
        0.930357,
        -0.681267
      ]
    },
    {
      "hoverinfo": "none",
      "line": {
        "color": "#9966cc",
        "shape": "linear",
        "width": 2.3846153846153846
      },
      "mode": "lines",
      "textposition": "middle center",
      "type": "scatter",
      "x": [
        -0.849857,
        -0.0398
      ],
      "y": [
        -0.208073,
        -0.863789
      ]
    },
    {
      "hoverinfo": "none",
      "line": {
        "color": "#9966cc",
        "shape": "linear",
        "width": 1.6923076923076923
      },
      "mode": "lines",
      "textposition": "middle center",
      "type": "scatter",
      "x": [
        -0.922743,
        -0.732027
      ],
      "y": [
        0.064301,
        0.357904
      ]
    },
    {
      "hoverinfo": "none",
      "line": {
        "color": "#9966cc",
        "shape": "linear",
        "width": 1.6923076923076923
      },
      "mode": "lines",
      "textposition": "middle center",
      "type": "scatter",
      "x": [
        0.025478,
        -0.548487
      ],
      "y": [
        0.930357,
        0.764706
      ]
    },
    {
      "hoverinfo": "none",
      "line": {
        "color": "#9966cc",
        "shape": "spline",
        "width": 1.6923076923076923
      },
      "mode": "lines",
      "textposition": "middle center",
      "type": "scatter",
      "x": [
        0.025478,
        0.40168090438599996,
        0.700297
      ],
      "y": [
        0.930357,
        0.8703110821427333,
        0.633747
      ]
    },
    {
      "hoverinfo": "none",
      "line": {
        "color": "#9966cc",
        "shape": "spline",
        "width": 1.6923076923076923
      },
      "mode": "lines",
      "textposition": "middle center",
      "type": "scatter",
      "x": [
        0.700297,
        0.324094095614,
        0.025478
      ],
      "y": [
        0.633747,
        0.6937929178572666,
        0.930357
      ]
    },
    {
      "hoverinfo": "none",
      "line": {
        "color": "#9966cc",
        "shape": "linear",
        "width": 2.3846153846153846
      },
      "mode": "lines",
      "textposition": "middle center",
      "type": "scatter",
      "x": [
        -0.77979,
        0.025478
      ],
      "y": [
        -0.133894,
        0.930357
      ]
    },
    {
      "hoverinfo": "none",
      "line": {
        "color": "#9966cc",
        "shape": "linear",
        "width": 5.153846153846154
      },
      "mode": "lines",
      "textposition": "middle center",
      "type": "scatter",
      "x": [
        -0.781294,
        0.025478
      ],
      "y": [
        -0.703002,
        0.930357
      ]
    },
    {
      "hoverinfo": "none",
      "line": {
        "color": "#9966cc",
        "shape": "linear",
        "width": 1.6923076923076923
      },
      "mode": "lines",
      "textposition": "middle center",
      "type": "scatter",
      "x": [
        -0.849857,
        -0.781294
      ],
      "y": [
        -0.208073,
        -0.703002
      ]
    },
    {
      "hoverinfo": "none",
      "line": {
        "color": "#9966cc",
        "shape": "linear",
        "width": 1.6923076923076923
      },
      "mode": "lines",
      "textposition": "middle center",
      "type": "scatter",
      "x": [
        -0.849857,
        -0.721001
      ],
      "y": [
        -0.208073,
        -0.536664
      ]
    },
    {
      "hoverinfo": "none",
      "line": {
        "color": "#9966cc",
        "shape": "linear",
        "width": 2.3846153846153846
      },
      "mode": "lines",
      "textposition": "middle center",
      "type": "scatter",
      "x": [
        0.626147,
        -0.091909
      ],
      "y": [
        -0.552137,
        -0.773046
      ]
    },
    {
      "hoverinfo": "none",
      "line": {
        "color": "#9966cc",
        "shape": "linear",
        "width": 2.3846153846153846
      },
      "mode": "lines",
      "textposition": "middle center",
      "type": "scatter",
      "x": [
        -0.159344,
        -0.091909
      ],
      "y": [
        -0.988631,
        -0.773046
      ]
    },
    {
      "hoverinfo": "none",
      "line": {
        "color": "#9966cc",
        "shape": "linear",
        "width": 3.076923076923077
      },
      "mode": "lines",
      "textposition": "middle center",
      "type": "scatter",
      "x": [
        0.818378,
        -0.091909
      ],
      "y": [
        0.408639,
        -0.773046
      ]
    },
    {
      "hoverinfo": "none",
      "line": {
        "color": "#9966cc",
        "shape": "linear",
        "width": 6.538461538461538
      },
      "mode": "lines",
      "textposition": "middle center",
      "type": "scatter",
      "x": [
        -0.77979,
        -0.945292
      ],
      "y": [
        -0.133894,
        -0.319687
      ]
    },
    {
      "hoverinfo": "none",
      "line": {
        "color": "#9966cc",
        "shape": "linear",
        "width": 2.3846153846153846
      },
      "mode": "lines",
      "textposition": "middle center",
      "type": "scatter",
      "x": [
        0.767867,
        -0.631459
      ],
      "y": [
        -0.576653,
        0.678742
      ]
    },
    {
      "hoverinfo": "none",
      "line": {
        "color": "#9966cc",
        "shape": "linear",
        "width": 2.3846153846153846
      },
      "mode": "lines",
      "textposition": "middle center",
      "type": "scatter",
      "x": [
        0.626147,
        0.900269
      ],
      "y": [
        -0.552137,
        -0.229238
      ]
    },
    {
      "hoverinfo": "none",
      "line": {
        "color": "#9966cc",
        "shape": "linear",
        "width": 3.076923076923077
      },
      "mode": "lines",
      "textposition": "middle center",
      "type": "scatter",
      "x": [
        -0.159344,
        0.900269
      ],
      "y": [
        -0.988631,
        -0.229238
      ]
    },
    {
      "hoverinfo": "none",
      "line": {
        "color": "#9966cc",
        "shape": "linear",
        "width": 10.0
      },
      "mode": "lines",
      "textposition": "middle center",
      "type": "scatter",
      "x": [
        -0.159344,
        0.938253
      ],
      "y": [
        -0.988631,
        0.432791
      ]
    },
    {
      "hoverinfo": "none",
      "line": {
        "color": "#9966cc",
        "shape": "linear",
        "width": 8.615384615384615
      },
      "mode": "lines",
      "textposition": "middle center",
      "type": "scatter",
      "x": [
        0.818378,
        0.938253
      ],
      "y": [
        0.408639,
        0.432791
      ]
    },
    {
      "hoverinfo": "none",
      "line": {
        "color": "#9966cc",
        "shape": "linear",
        "width": 9.307692307692308
      },
      "mode": "lines",
      "textposition": "middle center",
      "type": "scatter",
      "x": [
        0.700297,
        -0.340752
      ],
      "y": [
        0.633747,
        0.926809
      ]
    },
    {
      "hoverinfo": "none",
      "line": {
        "color": "#9966cc",
        "shape": "linear",
        "width": 3.769230769230769
      },
      "mode": "lines",
      "textposition": "middle center",
      "type": "scatter",
      "x": [
        -0.781294,
        -0.895051
      ],
      "y": [
        -0.703002,
        -0.014615
      ]
    },
    {
      "hoverinfo": "none",
      "line": {
        "color": "#9966cc",
        "shape": "linear",
        "width": 1.6923076923076923
      },
      "mode": "lines",
      "textposition": "middle center",
      "type": "scatter",
      "x": [
        -0.721001,
        0.877742
      ],
      "y": [
        -0.536664,
        -0.560364
      ]
    },
    {
      "hoverinfo": "none",
      "line": {
        "color": "#9966cc",
        "shape": "linear",
        "width": 2.3846153846153846
      },
      "mode": "lines",
      "textposition": "middle center",
      "type": "scatter",
      "x": [
        -0.171877,
        0.128843
      ],
      "y": [
        0.946475,
        -1.0
      ]
    },
    {
      "hoverinfo": "none",
      "line": {
        "color": "#9966cc",
        "shape": "linear",
        "width": 1.6923076923076923
      },
      "mode": "lines",
      "textposition": "middle center",
      "type": "scatter",
      "x": [
        -0.171877,
        0.077139
      ],
      "y": [
        0.946475,
        -0.813733
      ]
    },
    {
      "hoverinfo": "none",
      "line": {
        "color": "#9966cc",
        "shape": "linear",
        "width": 3.076923076923077
      },
      "mode": "lines",
      "textposition": "middle center",
      "type": "scatter",
      "x": [
        -0.261984,
        0.077139
      ],
      "y": [
        -0.698157,
        -0.813733
      ]
    },
    {
      "hoverinfo": "none",
      "line": {
        "color": "#9966cc",
        "shape": "linear",
        "width": 2.3846153846153846
      },
      "mode": "lines",
      "textposition": "middle center",
      "type": "scatter",
      "x": [
        -0.709278,
        0.885793
      ],
      "y": [
        0.468486,
        0.025389
      ]
    },
    {
      "hoverinfo": "none",
      "line": {
        "color": "#9966cc",
        "shape": "linear",
        "width": 2.3846153846153846
      },
      "mode": "lines",
      "textposition": "middle center",
      "type": "scatter",
      "x": [
        0.54915,
        -0.705268
      ],
      "y": [
        0.610682,
        -0.429377
      ]
    },
    {
      "hoverinfo": "none",
      "line": {
        "color": "#9966cc",
        "shape": "linear",
        "width": 1.6923076923076923
      },
      "mode": "lines",
      "textposition": "middle center",
      "type": "scatter",
      "x": [
        0.54915,
        -0.708817
      ],
      "y": [
        0.610682,
        0.778594
      ]
    },
    {
      "hoverinfo": "none",
      "line": {
        "color": "#9966cc",
        "shape": "linear",
        "width": 3.076923076923077
      },
      "mode": "lines",
      "textposition": "middle center",
      "type": "scatter",
      "x": [
        0.218891,
        -0.708817
      ],
      "y": [
        0.904351,
        0.778594
      ]
    },
    {
      "hoverinfo": "none",
      "line": {
        "color": "#9966cc",
        "shape": "linear",
        "width": 4.461538461538462
      },
      "mode": "lines",
      "textposition": "middle center",
      "type": "scatter",
      "x": [
        -0.77979,
        0.577462
      ],
      "y": [
        -0.133894,
        0.825893
      ]
    },
    {
      "hoverinfo": "none",
      "line": {
        "color": "#9966cc",
        "shape": "linear",
        "width": 1.6923076923076923
      },
      "mode": "lines",
      "textposition": "middle center",
      "type": "scatter",
      "x": [
        -0.171877,
        0.577462
      ],
      "y": [
        0.946475,
        0.825893
      ]
    },
    {
      "hoverinfo": "none",
      "line": {
        "color": "#9966cc",
        "shape": "linear",
        "width": 1.6923076923076923
      },
      "mode": "lines",
      "textposition": "middle center",
      "type": "scatter",
      "x": [
        0.626147,
        0.893483
      ],
      "y": [
        -0.552137,
        0.317487
      ]
    },
    {
      "hoverinfo": "none",
      "line": {
        "color": "#9966cc",
        "shape": "linear",
        "width": 1.6923076923076923
      },
      "mode": "lines",
      "textposition": "middle center",
      "type": "scatter",
      "x": [
        -0.159344,
        0.620719
      ],
      "y": [
        -0.988631,
        0.709951
      ]
    },
    {
      "hoverinfo": "none",
      "line": {
        "color": "#9966cc",
        "shape": "linear",
        "width": 3.769230769230769
      },
      "mode": "lines",
      "textposition": "middle center",
      "type": "scatter",
      "x": [
        0.700297,
        -0.548487
      ],
      "y": [
        0.633747,
        0.764706
      ]
    },
    {
      "hoverinfo": "none",
      "line": {
        "color": "#9966cc",
        "shape": "linear",
        "width": 2.3846153846153846
      },
      "mode": "lines",
      "textposition": "middle center",
      "type": "scatter",
      "x": [
        -0.781294,
        -0.548487
      ],
      "y": [
        -0.703002,
        0.764706
      ]
    },
    {
      "hoverinfo": "none",
      "line": {
        "color": "#9966cc",
        "shape": "linear",
        "width": 1.6923076923076923
      },
      "mode": "lines",
      "textposition": "middle center",
      "type": "scatter",
      "x": [
        -0.781294,
        0.79802
      ],
      "y": [
        -0.703002,
        0.139811
      ]
    },
    {
      "hoverinfo": "none",
      "line": {
        "color": "#9966cc",
        "shape": "linear",
        "width": 2.3846153846153846
      },
      "mode": "lines",
      "textposition": "middle center",
      "type": "scatter",
      "x": [
        -0.721001,
        0.79802
      ],
      "y": [
        -0.536664,
        0.139811
      ]
    },
    {
      "hoverinfo": "none",
      "line": {
        "color": "#9966cc",
        "shape": "linear",
        "width": 2.3846153846153846
      },
      "mode": "lines",
      "textposition": "middle center",
      "type": "scatter",
      "x": [
        -0.171877,
        -0.882497
      ],
      "y": [
        0.946475,
        -0.539267
      ]
    },
    {
      "hoverinfo": "none",
      "line": {
        "color": "#9966cc",
        "shape": "linear",
        "width": 1.6923076923076923
      },
      "mode": "lines",
      "textposition": "middle center",
      "type": "scatter",
      "x": [
        -0.261984,
        -0.795948
      ],
      "y": [
        -0.698157,
        -0.331804
      ]
    },
    {
      "hoverinfo": "none",
      "line": {
        "color": "#9966cc",
        "shape": "linear",
        "width": 2.3846153846153846
      },
      "mode": "lines",
      "textposition": "middle center",
      "type": "scatter",
      "x": [
        -0.709278,
        0.268128
      ],
      "y": [
        0.468486,
        -0.804213
      ]
    },
    {
      "hoverinfo": "none",
      "line": {
        "color": "#9966cc",
        "shape": "linear",
        "width": 1.6923076923076923
      },
      "mode": "lines",
      "textposition": "middle center",
      "type": "scatter",
      "x": [
        -0.709278,
        0.56542
      ],
      "y": [
        0.468486,
        -0.669812
      ]
    },
    {
      "hoverinfo": "none",
      "line": {
        "color": "#9966cc",
        "shape": "linear",
        "width": 2.3846153846153846
      },
      "mode": "lines",
      "textposition": "middle center",
      "type": "scatter",
      "x": [
        0.54915,
        0.56542
      ],
      "y": [
        0.610682,
        -0.669812
      ]
    },
    {
      "hoverinfo": "none",
      "line": {
        "color": "#9966cc",
        "shape": "linear",
        "width": 2.3846153846153846
      },
      "mode": "lines",
      "textposition": "middle center",
      "type": "scatter",
      "x": [
        0.218891,
        0.080581
      ],
      "y": [
        0.904351,
        0.898124
      ]
    },
    {
      "hoverinfo": "none",
      "line": {
        "color": "#9966cc",
        "shape": "linear",
        "width": 1.6923076923076923
      },
      "mode": "lines",
      "textposition": "middle center",
      "type": "scatter",
      "x": [
        0.767867,
        -0.88047
      ],
      "y": [
        -0.576653,
        0.573051
      ]
    },
    {
      "hoverinfo": "none",
      "line": {
        "color": "#9966cc",
        "shape": "linear",
        "width": 1.6923076923076923
      },
      "mode": "lines",
      "textposition": "middle center",
      "type": "scatter",
      "x": [
        0.818378,
        -0.159344
      ],
      "y": [
        0.408639,
        -0.988631
      ]
    },
    {
      "hoverinfo": "text",
      "hovertext": [
        "<b>AS1</b><br>Ventral cord motor neuron<br>Conns in: <b>VD2</b>: 1",
        "<b>AS10</b><br>Ventral cord motor neuron",
        "<b>AS11</b><br>Ventral cord motor neuron",
        "<b>AS2</b><br>Ventral cord motor neuron",
        "<b>AS3</b><br>Ventral cord motor neuron",
        "<b>AS4</b><br>Ventral cord motor neuron",
        "<b>AS5</b><br>Ventral cord motor neuron",
        "<b>AS6</b><br>Ventral cord motor neuron",
        "<b>AS7</b><br>Ventral cord motor neuron",
        "<b>AS8</b><br>Ventral cord motor neuron",
        "<b>AS9</b><br>Ventral cord motor neuron",
        "<b>DA1</b><br>Ventral cord motor neuron",
        "<b>DA2</b><br>Ventral cord motor neuron<br>Conns in: <b>DD1</b>: 3",
        "<b>DA3</b><br>Ventral cord motor neuron<br>Conns in: <b>DD2</b>: 2",
        "<b>DA4</b><br>Ventral cord motor neuron",
        "<b>DA5</b><br>Ventral cord motor neuron<br>Conns in: <b>DD3</b>: 1",
        "<b>DA6</b><br>Ventral cord motor neuron",
        "<b>DA7</b><br>Ventral cord motor neuron",
        "<b>DA8</b><br>Ventral cord motor neuron",
        "<b>DA9</b><br>Ventral cord motor neuron",
        "<b>DB1</b><br>Ventral cord motor neuron",
        "<b>DB2</b><br>Ventral cord motor neuron",
        "<b>DB3</b><br>Ventral cord motor neuron",
        "<b>DB4</b><br>Ventral cord motor neuron",
        "<b>DB5</b><br>Ventral cord motor neuron",
        "<b>DB6</b><br>Ventral cord motor neuron",
        "<b>DB7</b><br>Ventral cord motor neuron",
        "<b>DD1</b><br>Ventral cord motor neuron<br>Conns in: <b>VD3</b>: 6, <b>VD1</b>: 2, <b>VD2</b>: 1<br>Conns out: <b>DA2</b>: 3, <b>VB2</b>: 1, <b>VD2</b>: 1",
        "<b>DD2</b><br>Ventral cord motor neuron<br>Conns out: <b>DA3</b>: 2, <b>VD3</b>: 1, <b>VD4</b>: 1",
        "<b>DD3</b><br>Ventral cord motor neuron<br>Conns out: <b>DA5</b>: 1",
        "<b>DD4</b><br>Ventral cord motor neuron",
        "<b>DD5</b><br>Ventral cord motor neuron",
        "<b>DD6</b><br>Ventral cord motor neuron<br>Conns in: <b>VD13</b>: 3, <b>VD11</b>: 2, <b>VD12</b>: 2",
        "<b>HSNL</b><br>Hermaphrodite specific motor neuron",
        "<b>HSNR</b><br>Hermaphrodite specific motor neuron",
        "<b>PDA</b><br>Ventral cord motor neuron",
        "<b>PDB</b><br>Ventral cord motor neuron",
        "<b>RIVL</b><br>Head motor neuron",
        "<b>RIVR</b><br>Head motor neuron",
        "<b>RMDDL</b><br>Head motor neuron",
        "<b>RMDDR</b><br>Head motor neuron",
        "<b>RMDL</b><br>Head motor neuron",
        "<b>RMDR</b><br>Head motor neuron",
        "<b>RMDVL</b><br>Head motor neuron",
        "<b>RMDVR</b><br>Head motor neuron",
        "<b>RMED</b><br>Head motor neuron",
        "<b>RMEL</b><br>Head motor neuron",
        "<b>RMER</b><br>Head motor neuron",
        "<b>RMEV</b><br>Head motor neuron",
        "<b>RMHL</b><br>Head motor neuron",
        "<b>RMHR</b><br>Head motor neuron",
        "<b>SABD</b><br>Sublateral motor neuron; interneuron in White et al., 1986",
        "<b>SABVL</b><br>Sublateral motor neuron; interneuron in White et al., 1986",
        "<b>SABVR</b><br>Sublateral motor neuron; interneuron in White et al., 1986",
        "<b>SIADL</b><br>Sublateral motor neuron; interneuron in White et al., 1986",
        "<b>SIADR</b><br>Sublateral motor neuron; interneuron in White et al., 1986",
        "<b>SIAVL</b><br>Sublateral motor neuron; interneuron in White et al., 1986",
        "<b>SIAVR</b><br>Sublateral motor neuron; interneuron in White et al., 1986",
        "<b>SIBDL</b><br>Sublateral motor neuron; interneuron in White et al., 1986",
        "<b>SIBDR</b><br>Sublateral motor neuron; interneuron in White et al., 1986",
        "<b>SIBVL</b><br>Sublateral motor neuron; interneuron in White et al., 1986",
        "<b>SIBVR</b><br>Sublateral motor neuron; interneuron in White et al., 1986",
        "<b>SMBDL</b><br>Sublateral motor neuron",
        "<b>SMBDR</b><br>Sublateral motor neuron",
        "<b>SMBVL</b><br>Sublateral motor neuron",
        "<b>SMBVR</b><br>Sublateral motor neuron",
        "<b>SMDDL</b><br>Sublateral motor neuron",
        "<b>SMDDR</b><br>Sublateral motor neuron",
        "<b>SMDVL</b><br>Sublateral motor neuron",
        "<b>SMDVR</b><br>Sublateral motor neuron",
        "<b>URADL</b><br>Head motor neuron",
        "<b>URADR</b><br>Head motor neuron",
        "<b>URAVL</b><br>Head motor neuron",
        "<b>URAVR</b><br>Head motor neuron",
        "<b>VA1</b><br>Ventral cord motor neuron<br>Conns in: <b>VD1</b>: 8",
        "<b>VA10</b><br>Ventral cord motor neuron<br>Conns in: <b>VD10</b>: 2",
        "<b>VA11</b><br>Ventral cord motor neuron<br>Conns in: <b>VD12</b>: 3, <b>VD11</b>: 2",
        "<b>VA12</b><br>Ventral cord motor neuron<br>Conns in: <b>VD12</b>: 13, <b>VD13</b>: 11",
        "<b>VA2</b><br>Ventral cord motor neuron<br>Conns in: <b>VD2</b>: 12",
        "<b>VA3</b><br>Ventral cord motor neuron<br>Conns in: <b>VD3</b>: 4",
        "<b>VA4</b><br>Ventral cord motor neuron<br>Conns in: <b>VD4</b>: 1",
        "<b>VA5</b><br>Ventral cord motor neuron<br>Conns in: <b>VD5</b>: 2",
        "<b>VA6</b><br>Ventral cord motor neuron<br>Conns in: <b>VD6</b>: 3, <b>VD5</b>: 1",
        "<b>VA7</b><br>Ventral cord motor neuron<br>Conns in: <b>VD7</b>: 2",
        "<b>VA8</b><br>Ventral cord motor neuron<br>Conns in: <b>VD8</b>: 2",
        "<b>VA9</b><br>Ventral cord motor neuron<br>Conns in: <b>VD9</b>: 3, <b>VD8</b>: 1",
        "<b>VB1</b><br>Ventral cord motor neuron<br>Conns in: <b>VD1</b>: 5, <b>VD5</b>: 1",
        "<b>VB10</b><br>Ventral cord motor neuron<br>Conns in: <b>VD11</b>: 1",
        "<b>VB11</b><br>Ventral cord motor neuron<br>Conns in: <b>VD12</b>: 1",
        "<b>VB2</b><br>Ventral cord motor neuron<br>Conns in: <b>VD2</b>: 4, <b>VD3</b>: 2, <b>DD1</b>: 1",
        "<b>VB3</b><br>Ventral cord motor neuron<br>Conns in: <b>VD4</b>: 2, <b>VD3</b>: 1",
        "<b>VB4</b><br>Ventral cord motor neuron<br>Conns in: <b>VD5</b>: 2",
        "<b>VB5</b><br>Ventral cord motor neuron<br>Conns in: <b>VD6</b>: 1",
        "<b>VB6</b><br>Ventral cord motor neuron<br>Conns in: <b>VD7</b>: 2",
        "<b>VB7</b><br>Ventral cord motor neuron<br>Conns in: <b>VD8</b>: 2, <b>VD7</b>: 1",
        "<b>VB8</b><br>Ventral cord motor neuron<br>Conns in: <b>VD9</b>: 2",
        "<b>VB9</b><br>Ventral cord motor neuron<br>Conns in: <b>VD10</b>: 1",
        "<b>VC1</b><br>Hermaphrodite specific motor neuron",
        "<b>VC2</b><br>Hermaphrodite specific motor neuron",
        "<b>VC3</b><br>Hermaphrodite specific motor neuron",
        "<b>VC4</b><br>Hermaphrodite specific motor neuron",
        "<b>VC5</b><br>Hermaphrodite specific motor neuron",
        "<b>VC6</b><br>Hermaphrodite specific motor neuron",
        "<b>VD1</b><br>Ventral cord motor neuron<br>Conns out: <b>VA1</b>: 8, <b>VB1</b>: 5, <b>DD1</b>: 2",
        "<b>VD10</b><br>Ventral cord motor neuron<br>Conns out: <b>VA10</b>: 2, <b>VB9</b>: 1",
        "<b>VD11</b><br>Ventral cord motor neuron<br>Conns out: <b>DD6</b>: 2, <b>VA11</b>: 2, <b>VB10</b>: 1",
        "<b>VD12</b><br>Ventral cord motor neuron<br>Conns in: <b>VD13</b>: 1<br>Conns out: <b>VA12</b>: 13, <b>VA11</b>: 3, <b>DD6</b>: 2, <b>VB11</b>: 1",
        "<b>VD13</b><br>Ventral cord motor neuron<br>Conns out: <b>VA12</b>: 11, <b>DD6</b>: 3, <b>VD12</b>: 1",
        "<b>VD2</b><br>Ventral cord motor neuron<br>Conns in: <b>DD1</b>: 1<br>Conns out: <b>VA2</b>: 12, <b>VB2</b>: 4, <b>AS1</b>: 1, <b>DD1</b>: 1",
        "<b>VD3</b><br>Ventral cord motor neuron<br>Conns in: <b>DD2</b>: 1<br>Conns out: <b>DD1</b>: 6, <b>VA3</b>: 4, <b>VB2</b>: 2, <b>VB3</b>: 1",
        "<b>VD4</b><br>Ventral cord motor neuron<br>Conns in: <b>DD2</b>: 1<br>Conns out: <b>VB3</b>: 2, <b>VA4</b>: 1",
        "<b>VD5</b><br>Ventral cord motor neuron<br>Conns out: <b>VA5</b>: 2, <b>VB4</b>: 2, <b>VA6</b>: 1, <b>VB1</b>: 1",
        "<b>VD6</b><br>Ventral cord motor neuron<br>Conns out: <b>VA6</b>: 3, <b>VB5</b>: 1",
        "<b>VD7</b><br>Ventral cord motor neuron<br>Conns out: <b>VA7</b>: 2, <b>VB6</b>: 2, <b>VB7</b>: 1",
        "<b>VD8</b><br>Ventral cord motor neuron<br>Conns out: <b>VA8</b>: 2, <b>VB7</b>: 2, <b>VA9</b>: 1",
        "<b>VD9</b><br>Ventral cord motor neuron<br>Conns out: <b>VA9</b>: 3, <b>VB8</b>: 2"
      ],
      "marker": {
        "color": [
          "#9966cc",
          "#9966cc",
          "#9966cc",
          "#9966cc",
          "#9966cc",
          "#9966cc",
          "#9966cc",
          "#9966cc",
          "#9966cc",
          "#9966cc",
          "#9966cc",
          "#9966cc",
          "#9966cc",
          "#9966cc",
          "#9966cc",
          "#9966cc",
          "#9966cc",
          "#9966cc",
          "#9966cc",
          "#9966cc",
          "#9966cc",
          "#9966cc",
          "#9966cc",
          "#9966cc",
          "#9966cc",
          "#9966cc",
          "#9966cc",
          "#9966cc",
          "#9966cc",
          "#9966cc",
          "#9966cc",
          "#9966cc",
          "#9966cc",
          "#9966cc",
          "#9966cc",
          "#9966cc",
          "#9966cc",
          "#9966cc",
          "#9966cc",
          "#9966cc",
          "#9966cc",
          "#9966cc",
          "#9966cc",
          "#9966cc",
          "#9966cc",
          "#9966cc",
          "#9966cc",
          "#9966cc",
          "#9966cc",
          "#9966cc",
          "#9966cc",
          "#9966cc",
          "#9966cc",
          "#9966cc",
          "#9966cc",
          "#9966cc",
          "#9966cc",
          "#9966cc",
          "#9966cc",
          "#9966cc",
          "#9966cc",
          "#9966cc",
          "#9966cc",
          "#9966cc",
          "#9966cc",
          "#9966cc",
          "#9966cc",
          "#9966cc",
          "#9966cc",
          "#9966cc",
          "#9966cc",
          "#9966cc",
          "#9966cc",
          "#9966cc",
          "#9966cc",
          "#9966cc",
          "#9966cc",
          "#9966cc",
          "#9966cc",
          "#9966cc",
          "#9966cc",
          "#9966cc",
          "#9966cc",
          "#9966cc",
          "#9966cc",
          "#9966cc",
          "#9966cc",
          "#9966cc",
          "#9966cc",
          "#9966cc",
          "#9966cc",
          "#9966cc",
          "#9966cc",
          "#9966cc",
          "#9966cc",
          "#9966cc",
          "#9966cc",
          "#9966cc",
          "#9966cc",
          "#9966cc",
          "#9966cc",
          "#9966cc",
          "#9966cc",
          "#9966cc",
          "#9966cc",
          "#9966cc",
          "#9966cc",
          "#9966cc",
          "#9966cc",
          "#9966cc",
          "#9966cc",
          "#9966cc",
          "#9966cc",
          "#9966cc",
          "#9966cc",
          "#9966cc"
        ],
        "colorbar": {
          "thickness": 15,
          "title": {
            "text": "Node Connections"
          },
          "xanchor": "left"
        },
        "colorscale": [
          [
            0.0,
            "rgb(255,255,217)"
          ],
          [
            0.125,
            "rgb(237,248,177)"
          ],
          [
            0.25,
            "rgb(199,233,180)"
          ],
          [
            0.375,
            "rgb(127,205,187)"
          ],
          [
            0.5,
            "rgb(65,182,196)"
          ],
          [
            0.625,
            "rgb(29,145,192)"
          ],
          [
            0.75,
            "rgb(34,94,168)"
          ],
          [
            0.875,
            "rgb(37,52,148)"
          ],
          [
            1.0,
            "rgb(8,29,88)"
          ]
        ],
        "line": {
          "width": 1
        },
        "reversescale": true,
        "showscale": false,
        "size": [
          15.0,
          15.0,
          15.0,
          15.0,
          15.0,
          15.0,
          15.0,
          15.0,
          15.0,
          15.0,
          15.0,
          15.0,
          15.0,
          15.0,
          15.0,
          15.0,
          15.0,
          15.0,
          15.0,
          15.0,
          15.0,
          15.0,
          15.0,
          15.0,
          15.0,
          15.0,
          15.0,
          15.0,
          15.0,
          15.0,
          15.0,
          15.0,
          15.0,
          15.0,
          15.0,
          15.0,
          15.0,
          15.0,
          15.0,
          15.0,
          15.0,
          15.0,
          15.0,
          15.0,
          15.0,
          15.0,
          15.0,
          15.0,
          15.0,
          15.0,
          15.0,
          15.0,
          15.0,
          15.0,
          15.0,
          15.0,
          15.0,
          15.0,
          15.0,
          15.0,
          15.0,
          15.0,
          15.0,
          15.0,
          15.0,
          15.0,
          15.0,
          15.0,
          15.0,
          15.0,
          15.0,
          15.0,
          15.0,
          15.0,
          15.0,
          15.0,
          15.0,
          15.0,
          15.0,
          15.0,
          15.0,
          15.0,
          15.0,
          15.0,
          15.0,
          15.0,
          15.0,
          15.0,
          15.0,
          15.0,
          15.0,
          15.0,
          15.0,
          15.0,
          15.0,
          15.0,
          15.0,
          15.0,
          15.0,
          15.0,
          15.0,
          15.0,
          15.0,
          15.0,
          15.0,
          15.0,
          15.0,
          15.0,
          15.0,
          15.0,
          15.0,
          15.0,
          15.0,
          15.0,
          15.0,
          15.0
        ],
        "symbol": [
          "circle",
          "circle",
          "circle",
          "circle",
          "circle",
          "circle",
          "circle",
          "circle",
          "circle",
          "circle",
          "circle",
          "circle",
          "circle",
          "circle",
          "circle",
          "circle",
          "circle",
          "circle",
          "circle",
          "circle",
          "circle",
          "circle",
          "circle",
          "circle",
          "circle",
          "circle",
          "circle",
          "circle",
          "circle",
          "circle",
          "circle",
          "circle",
          "circle",
          "circle",
          "circle",
          "circle",
          "circle",
          "circle",
          "circle",
          "circle",
          "circle",
          "circle",
          "circle",
          "circle",
          "circle",
          "circle",
          "circle",
          "circle",
          "circle",
          "circle",
          "circle",
          "circle",
          "circle",
          "circle",
          "circle",
          "circle",
          "circle",
          "circle",
          "circle",
          "circle",
          "circle",
          "circle",
          "circle",
          "circle",
          "circle",
          "circle",
          "circle",
          "circle",
          "circle",
          "circle",
          "circle",
          "circle",
          "circle",
          "circle",
          "circle",
          "circle",
          "circle",
          "circle",
          "circle",
          "circle",
          "circle",
          "circle",
          "circle",
          "circle",
          "circle",
          "circle",
          "circle",
          "circle",
          "circle",
          "circle",
          "circle",
          "circle",
          "circle",
          "circle",
          "circle",
          "circle",
          "circle",
          "circle",
          "circle",
          "circle",
          "circle",
          "circle",
          "circle",
          "circle",
          "circle",
          "circle",
          "circle",
          "circle",
          "circle",
          "circle",
          "circle",
          "circle",
          "circle",
          "circle",
          "circle",
          "circle"
        ]
      },
      "mode": "markers",
      "opacity": 1,
      "text": [
        "<span style=\"color:#000000;font-size:1.0em\"><b>AS1</b></span>",
        "<span style=\"color:#000000;font-size:1.0em\"><b>AS10</b></span>",
        "<span style=\"color:#000000;font-size:1.0em\"><b>AS11</b></span>",
        "<span style=\"color:#000000;font-size:1.0em\"><b>AS2</b></span>",
        "<span style=\"color:#000000;font-size:1.0em\"><b>AS3</b></span>",
        "<span style=\"color:#000000;font-size:1.0em\"><b>AS4</b></span>",
        "<span style=\"color:#000000;font-size:1.0em\"><b>AS5</b></span>",
        "<span style=\"color:#000000;font-size:1.0em\"><b>AS6</b></span>",
        "<span style=\"color:#000000;font-size:1.0em\"><b>AS7</b></span>",
        "<span style=\"color:#000000;font-size:1.0em\"><b>AS8</b></span>",
        "<span style=\"color:#000000;font-size:1.0em\"><b>AS9</b></span>",
        "<span style=\"color:#000000;font-size:1.0em\"><b>DA1</b></span>",
        "<span style=\"color:#000000;font-size:1.0em\"><b>DA2</b></span>",
        "<span style=\"color:#000000;font-size:1.0em\"><b>DA3</b></span>",
        "<span style=\"color:#000000;font-size:1.0em\"><b>DA4</b></span>",
        "<span style=\"color:#000000;font-size:1.0em\"><b>DA5</b></span>",
        "<span style=\"color:#000000;font-size:1.0em\"><b>DA6</b></span>",
        "<span style=\"color:#000000;font-size:1.0em\"><b>DA7</b></span>",
        "<span style=\"color:#000000;font-size:1.0em\"><b>DA8</b></span>",
        "<span style=\"color:#000000;font-size:1.0em\"><b>DA9</b></span>",
        "<span style=\"color:#000000;font-size:1.0em\"><b>DB1</b></span>",
        "<span style=\"color:#000000;font-size:1.0em\"><b>DB2</b></span>",
        "<span style=\"color:#000000;font-size:1.0em\"><b>DB3</b></span>",
        "<span style=\"color:#000000;font-size:1.0em\"><b>DB4</b></span>",
        "<span style=\"color:#000000;font-size:1.0em\"><b>DB5</b></span>",
        "<span style=\"color:#000000;font-size:1.0em\"><b>DB6</b></span>",
        "<span style=\"color:#000000;font-size:1.0em\"><b>DB7</b></span>",
        "<span style=\"color:#000000;font-size:1.0em\"><b>DD1</b></span>",
        "<span style=\"color:#000000;font-size:1.0em\"><b>DD2</b></span>",
        "<span style=\"color:#000000;font-size:1.0em\"><b>DD3</b></span>",
        "<span style=\"color:#000000;font-size:1.0em\"><b>DD4</b></span>",
        "<span style=\"color:#000000;font-size:1.0em\"><b>DD5</b></span>",
        "<span style=\"color:#000000;font-size:1.0em\"><b>DD6</b></span>",
        "<span style=\"color:#000000;font-size:1.0em\"><b>HSNL</b></span>",
        "<span style=\"color:#000000;font-size:1.0em\"><b>HSNR</b></span>",
        "<span style=\"color:#000000;font-size:1.0em\"><b>PDA</b></span>",
        "<span style=\"color:#000000;font-size:1.0em\"><b>PDB</b></span>",
        "<span style=\"color:#000000;font-size:1.0em\"><b>RIVL</b></span>",
        "<span style=\"color:#000000;font-size:1.0em\"><b>RIVR</b></span>",
        "<span style=\"color:#000000;font-size:1.0em\"><b>RMDDL</b></span>",
        "<span style=\"color:#000000;font-size:1.0em\"><b>RMDDR</b></span>",
        "<span style=\"color:#000000;font-size:1.0em\"><b>RMDL</b></span>",
        "<span style=\"color:#000000;font-size:1.0em\"><b>RMDR</b></span>",
        "<span style=\"color:#000000;font-size:1.0em\"><b>RMDVL</b></span>",
        "<span style=\"color:#000000;font-size:1.0em\"><b>RMDVR</b></span>",
        "<span style=\"color:#000000;font-size:1.0em\"><b>RMED</b></span>",
        "<span style=\"color:#000000;font-size:1.0em\"><b>RMEL</b></span>",
        "<span style=\"color:#000000;font-size:1.0em\"><b>RMER</b></span>",
        "<span style=\"color:#000000;font-size:1.0em\"><b>RMEV</b></span>",
        "<span style=\"color:#000000;font-size:1.0em\"><b>RMHL</b></span>",
        "<span style=\"color:#000000;font-size:1.0em\"><b>RMHR</b></span>",
        "<span style=\"color:#000000;font-size:1.0em\"><b>SABD</b></span>",
        "<span style=\"color:#000000;font-size:1.0em\"><b>SABVL</b></span>",
        "<span style=\"color:#000000;font-size:1.0em\"><b>SABVR</b></span>",
        "<span style=\"color:#000000;font-size:1.0em\"><b>SIADL</b></span>",
        "<span style=\"color:#000000;font-size:1.0em\"><b>SIADR</b></span>",
        "<span style=\"color:#000000;font-size:1.0em\"><b>SIAVL</b></span>",
        "<span style=\"color:#000000;font-size:1.0em\"><b>SIAVR</b></span>",
        "<span style=\"color:#000000;font-size:1.0em\"><b>SIBDL</b></span>",
        "<span style=\"color:#000000;font-size:1.0em\"><b>SIBDR</b></span>",
        "<span style=\"color:#000000;font-size:1.0em\"><b>SIBVL</b></span>",
        "<span style=\"color:#000000;font-size:1.0em\"><b>SIBVR</b></span>",
        "<span style=\"color:#000000;font-size:1.0em\"><b>SMBDL</b></span>",
        "<span style=\"color:#000000;font-size:1.0em\"><b>SMBDR</b></span>",
        "<span style=\"color:#000000;font-size:1.0em\"><b>SMBVL</b></span>",
        "<span style=\"color:#000000;font-size:1.0em\"><b>SMBVR</b></span>",
        "<span style=\"color:#000000;font-size:1.0em\"><b>SMDDL</b></span>",
        "<span style=\"color:#000000;font-size:1.0em\"><b>SMDDR</b></span>",
        "<span style=\"color:#000000;font-size:1.0em\"><b>SMDVL</b></span>",
        "<span style=\"color:#000000;font-size:1.0em\"><b>SMDVR</b></span>",
        "<span style=\"color:#000000;font-size:1.0em\"><b>URADL</b></span>",
        "<span style=\"color:#000000;font-size:1.0em\"><b>URADR</b></span>",
        "<span style=\"color:#000000;font-size:1.0em\"><b>URAVL</b></span>",
        "<span style=\"color:#000000;font-size:1.0em\"><b>URAVR</b></span>",
        "<span style=\"color:#000000;font-size:1.0em\"><b>VA1</b></span>",
        "<span style=\"color:#000000;font-size:1.0em\"><b>VA10</b></span>",
        "<span style=\"color:#000000;font-size:1.0em\"><b>VA11</b></span>",
        "<span style=\"color:#000000;font-size:1.0em\"><b>VA12</b></span>",
        "<span style=\"color:#000000;font-size:1.0em\"><b>VA2</b></span>",
        "<span style=\"color:#000000;font-size:1.0em\"><b>VA3</b></span>",
        "<span style=\"color:#000000;font-size:1.0em\"><b>VA4</b></span>",
        "<span style=\"color:#000000;font-size:1.0em\"><b>VA5</b></span>",
        "<span style=\"color:#000000;font-size:1.0em\"><b>VA6</b></span>",
        "<span style=\"color:#000000;font-size:1.0em\"><b>VA7</b></span>",
        "<span style=\"color:#000000;font-size:1.0em\"><b>VA8</b></span>",
        "<span style=\"color:#000000;font-size:1.0em\"><b>VA9</b></span>",
        "<span style=\"color:#000000;font-size:1.0em\"><b>VB1</b></span>",
        "<span style=\"color:#000000;font-size:1.0em\"><b>VB10</b></span>",
        "<span style=\"color:#000000;font-size:1.0em\"><b>VB11</b></span>",
        "<span style=\"color:#000000;font-size:1.0em\"><b>VB2</b></span>",
        "<span style=\"color:#000000;font-size:1.0em\"><b>VB3</b></span>",
        "<span style=\"color:#000000;font-size:1.0em\"><b>VB4</b></span>",
        "<span style=\"color:#000000;font-size:1.0em\"><b>VB5</b></span>",
        "<span style=\"color:#000000;font-size:1.0em\"><b>VB6</b></span>",
        "<span style=\"color:#000000;font-size:1.0em\"><b>VB7</b></span>",
        "<span style=\"color:#000000;font-size:1.0em\"><b>VB8</b></span>",
        "<span style=\"color:#000000;font-size:1.0em\"><b>VB9</b></span>",
        "<span style=\"color:#000000;font-size:1.0em\"><b>VC1</b></span>",
        "<span style=\"color:#000000;font-size:1.0em\"><b>VC2</b></span>",
        "<span style=\"color:#000000;font-size:1.0em\"><b>VC3</b></span>",
        "<span style=\"color:#000000;font-size:1.0em\"><b>VC4</b></span>",
        "<span style=\"color:#000000;font-size:1.0em\"><b>VC5</b></span>",
        "<span style=\"color:#000000;font-size:1.0em\"><b>VC6</b></span>",
        "<span style=\"color:#000000;font-size:1.0em\"><b>VD1</b></span>",
        "<span style=\"color:#000000;font-size:1.0em\"><b>VD10</b></span>",
        "<span style=\"color:#000000;font-size:1.0em\"><b>VD11</b></span>",
        "<span style=\"color:#000000;font-size:1.0em\"><b>VD12</b></span>",
        "<span style=\"color:#000000;font-size:1.0em\"><b>VD13</b></span>",
        "<span style=\"color:#000000;font-size:1.0em\"><b>VD2</b></span>",
        "<span style=\"color:#000000;font-size:1.0em\"><b>VD3</b></span>",
        "<span style=\"color:#000000;font-size:1.0em\"><b>VD4</b></span>",
        "<span style=\"color:#000000;font-size:1.0em\"><b>VD5</b></span>",
        "<span style=\"color:#000000;font-size:1.0em\"><b>VD6</b></span>",
        "<span style=\"color:#000000;font-size:1.0em\"><b>VD7</b></span>",
        "<span style=\"color:#000000;font-size:1.0em\"><b>VD8</b></span>",
        "<span style=\"color:#000000;font-size:1.0em\"><b>VD9</b></span>"
      ],
      "textposition": "middle center",
      "type": "scatter",
      "x": [
        -0.112176,
        -0.539793,
        0.652904,
        0.447769,
        0.668559,
        0.594773,
        -0.633418,
        -0.223491,
        0.425445,
        0.16767,
        0.788663,
        -0.440387,
        0.443082,
        -0.0398,
        0.912076,
        -0.732027,
        -0.889875,
        -0.52978,
        0.310195,
        -0.657582,
        -0.881086,
        0.883343,
        0.974775,
        0.377383,
        0.731492,
        -0.292688,
        -0.890466,
        0.025478,
        -0.849857,
        -0.922743,
        0.453524,
        -0.381224,
        -0.091909,
        -0.341925,
        0.753045,
        0.143833,
        0.767474,
        0.846397,
        0.010296,
        -0.957642,
        -0.789828,
        -0.815223,
        0.737468,
        -0.484851,
        -0.275876,
        -0.987064,
        0.274793,
        0.949314,
        0.517009,
        0.86606,
        -0.816734,
        -0.426196,
        0.769734,
        0.699219,
        0.734738,
        0.149097,
        -0.232914,
        -0.114095,
        -0.868474,
        0.933176,
        -0.657478,
        -0.895981,
        0.336811,
        -0.068603,
        -0.516738,
        0.24677,
        -0.594011,
        -0.550971,
        -0.729308,
        -0.398998,
        0.838515,
        -0.040258,
        -0.81099,
        0.41599,
        -0.945292,
        -0.631459,
        0.900269,
        0.938253,
        -0.340752,
        -0.895051,
        0.877742,
        0.128843,
        0.077139,
        0.885793,
        -0.705268,
        -0.708817,
        0.577462,
        0.893483,
        0.620719,
        -0.548487,
        0.79802,
        -0.882497,
        -0.795948,
        0.268128,
        0.56542,
        0.080581,
        -0.88047,
        0.875765,
        -0.930642,
        0.405901,
        -0.430125,
        0.813457,
        0.527259,
        -0.77979,
        0.767867,
        0.626147,
        -0.159344,
        0.818378,
        0.700297,
        -0.781294,
        -0.721001,
        -0.171877,
        -0.261984,
        -0.709278,
        0.54915,
        0.218891
      ],
      "y": [
        0.912221,
        -0.842937,
        0.408945,
        -0.928336,
        -0.716662,
        -0.788054,
        -0.567149,
        -0.836108,
        0.726405,
        -0.842131,
        0.566383,
        -0.786974,
        -0.681267,
        -0.863789,
        0.221251,
        0.357904,
        -0.287458,
        -0.533063,
        0.897956,
        -0.772692,
        0.229794,
        -0.427115,
        0.043404,
        0.839483,
        -0.39763,
        0.841341,
        0.327481,
        0.930357,
        -0.208073,
        0.064301,
        0.848402,
        0.789125,
        -0.773046,
        -0.767535,
        -0.678712,
        0.751003,
        0.283056,
        -0.150208,
        -0.99193,
        -0.130379,
        -0.428719,
        0.527502,
        0.717377,
        -0.685212,
        -0.932384,
        0.097357,
        0.820317,
        -0.138594,
        -0.853065,
        0.496258,
        0.296694,
        0.836463,
        -0.481925,
        0.521478,
        -0.162048,
        0.892167,
        0.895417,
        0.780439,
        0.424079,
        -0.321762,
        0.588022,
        -0.101083,
        -0.86893,
        -0.928468,
        0.701053,
        -0.955908,
        -0.66625,
        0.868508,
        0.600575,
        -0.904229,
        -0.041083,
        0.908282,
        0.094928,
        -0.435409,
        -0.319687,
        0.678742,
        -0.229238,
        0.432791,
        0.926809,
        -0.014615,
        -0.560364,
        -1.0,
        -0.813733,
        0.025389,
        -0.429377,
        0.778594,
        0.825893,
        0.317487,
        0.709951,
        0.764706,
        0.139811,
        -0.539267,
        -0.331804,
        -0.804213,
        -0.669812,
        0.898124,
        0.573051,
        0.139526,
        0.179079,
        -0.772768,
        0.629555,
        -0.312169,
        0.764886,
        -0.133894,
        -0.576653,
        -0.552137,
        -0.988631,
        0.408639,
        0.633747,
        -0.703002,
        -0.536664,
        0.946475,
        -0.698157,
        0.468486,
        0.610682,
        0.904351
      ]
    }
  ],
  "layout": {
    "height": 800,
    "hovermode": "closest",
    "margin": {
      "b": 20,
      "l": 5,
      "r": 5,
      "t": 40
    },
    "showlegend": false,
    "template": {
      "data": {
        "bar": [
          {
            "error_x": {
              "color": "#2a3f5f"
            },
            "error_y": {
              "color": "#2a3f5f"
            },
            "marker": {
              "line": {
                "color": "white",
                "width": 0.5
              },
              "pattern": {
                "fillmode": "overlay",
                "size": 10,
                "solidity": 0.2
              }
            },
            "type": "bar"
          }
        ],
        "barpolar": [
          {
            "marker": {
              "line": {
                "color": "white",
                "width": 0.5
              },
              "pattern": {
                "fillmode": "overlay",
                "size": 10,
                "solidity": 0.2
              }
            },
            "type": "barpolar"
          }
        ],
        "carpet": [
          {
            "aaxis": {
              "endlinecolor": "#2a3f5f",
              "gridcolor": "#C8D4E3",
              "linecolor": "#C8D4E3",
              "minorgridcolor": "#C8D4E3",
              "startlinecolor": "#2a3f5f"
            },
            "baxis": {
              "endlinecolor": "#2a3f5f",
              "gridcolor": "#C8D4E3",
              "linecolor": "#C8D4E3",
              "minorgridcolor": "#C8D4E3",
              "startlinecolor": "#2a3f5f"
            },
            "type": "carpet"
          }
        ],
        "choropleth": [
          {
            "colorbar": {
              "outlinewidth": 0,
              "ticks": ""
            },
            "type": "choropleth"
          }
        ],
        "contour": [
          {
            "colorbar": {
              "outlinewidth": 0,
              "ticks": ""
            },
            "colorscale": [
              [
                0.0,
                "#0d0887"
              ],
              [
                0.1111111111111111,
                "#46039f"
              ],
              [
                0.2222222222222222,
                "#7201a8"
              ],
              [
                0.3333333333333333,
                "#9c179e"
              ],
              [
                0.4444444444444444,
                "#bd3786"
              ],
              [
                0.5555555555555556,
                "#d8576b"
              ],
              [
                0.6666666666666666,
                "#ed7953"
              ],
              [
                0.7777777777777778,
                "#fb9f3a"
              ],
              [
                0.8888888888888888,
                "#fdca26"
              ],
              [
                1.0,
                "#f0f921"
              ]
            ],
            "type": "contour"
          }
        ],
        "contourcarpet": [
          {
            "colorbar": {
              "outlinewidth": 0,
              "ticks": ""
            },
            "type": "contourcarpet"
          }
        ],
        "heatmap": [
          {
            "colorbar": {
              "outlinewidth": 0,
              "ticks": ""
            },
            "colorscale": [
              [
                0.0,
                "#0d0887"
              ],
              [
                0.1111111111111111,
                "#46039f"
              ],
              [
                0.2222222222222222,
                "#7201a8"
              ],
              [
                0.3333333333333333,
                "#9c179e"
              ],
              [
                0.4444444444444444,
                "#bd3786"
              ],
              [
                0.5555555555555556,
                "#d8576b"
              ],
              [
                0.6666666666666666,
                "#ed7953"
              ],
              [
                0.7777777777777778,
                "#fb9f3a"
              ],
              [
                0.8888888888888888,
                "#fdca26"
              ],
              [
                1.0,
                "#f0f921"
              ]
            ],
            "type": "heatmap"
          }
        ],
        "heatmapgl": [
          {
            "colorbar": {
              "outlinewidth": 0,
              "ticks": ""
            },
            "colorscale": [
              [
                0.0,
                "#0d0887"
              ],
              [
                0.1111111111111111,
                "#46039f"
              ],
              [
                0.2222222222222222,
                "#7201a8"
              ],
              [
                0.3333333333333333,
                "#9c179e"
              ],
              [
                0.4444444444444444,
                "#bd3786"
              ],
              [
                0.5555555555555556,
                "#d8576b"
              ],
              [
                0.6666666666666666,
                "#ed7953"
              ],
              [
                0.7777777777777778,
                "#fb9f3a"
              ],
              [
                0.8888888888888888,
                "#fdca26"
              ],
              [
                1.0,
                "#f0f921"
              ]
            ],
            "type": "heatmapgl"
          }
        ],
        "histogram": [
          {
            "marker": {
              "pattern": {
                "fillmode": "overlay",
                "size": 10,
                "solidity": 0.2
              }
            },
            "type": "histogram"
          }
        ],
        "histogram2d": [
          {
            "colorbar": {
              "outlinewidth": 0,
              "ticks": ""
            },
            "colorscale": [
              [
                0.0,
                "#0d0887"
              ],
              [
                0.1111111111111111,
                "#46039f"
              ],
              [
                0.2222222222222222,
                "#7201a8"
              ],
              [
                0.3333333333333333,
                "#9c179e"
              ],
              [
                0.4444444444444444,
                "#bd3786"
              ],
              [
                0.5555555555555556,
                "#d8576b"
              ],
              [
                0.6666666666666666,
                "#ed7953"
              ],
              [
                0.7777777777777778,
                "#fb9f3a"
              ],
              [
                0.8888888888888888,
                "#fdca26"
              ],
              [
                1.0,
                "#f0f921"
              ]
            ],
            "type": "histogram2d"
          }
        ],
        "histogram2dcontour": [
          {
            "colorbar": {
              "outlinewidth": 0,
              "ticks": ""
            },
            "colorscale": [
              [
                0.0,
                "#0d0887"
              ],
              [
                0.1111111111111111,
                "#46039f"
              ],
              [
                0.2222222222222222,
                "#7201a8"
              ],
              [
                0.3333333333333333,
                "#9c179e"
              ],
              [
                0.4444444444444444,
                "#bd3786"
              ],
              [
                0.5555555555555556,
                "#d8576b"
              ],
              [
                0.6666666666666666,
                "#ed7953"
              ],
              [
                0.7777777777777778,
                "#fb9f3a"
              ],
              [
                0.8888888888888888,
                "#fdca26"
              ],
              [
                1.0,
                "#f0f921"
              ]
            ],
            "type": "histogram2dcontour"
          }
        ],
        "mesh3d": [
          {
            "colorbar": {
              "outlinewidth": 0,
              "ticks": ""
            },
            "type": "mesh3d"
          }
        ],
        "parcoords": [
          {
            "line": {
              "colorbar": {
                "outlinewidth": 0,
                "ticks": ""
              }
            },
            "type": "parcoords"
          }
        ],
        "pie": [
          {
            "automargin": true,
            "type": "pie"
          }
        ],
        "scatter": [
          {
            "fillpattern": {
              "fillmode": "overlay",
              "size": 10,
              "solidity": 0.2
            },
            "type": "scatter"
          }
        ],
        "scatter3d": [
          {
            "line": {
              "colorbar": {
                "outlinewidth": 0,
                "ticks": ""
              }
            },
            "marker": {
              "colorbar": {
                "outlinewidth": 0,
                "ticks": ""
              }
            },
            "type": "scatter3d"
          }
        ],
        "scattercarpet": [
          {
            "marker": {
              "colorbar": {
                "outlinewidth": 0,
                "ticks": ""
              }
            },
            "type": "scattercarpet"
          }
        ],
        "scattergeo": [
          {
            "marker": {
              "colorbar": {
                "outlinewidth": 0,
                "ticks": ""
              }
            },
            "type": "scattergeo"
          }
        ],
        "scattergl": [
          {
            "marker": {
              "colorbar": {
                "outlinewidth": 0,
                "ticks": ""
              }
            },
            "type": "scattergl"
          }
        ],
        "scattermapbox": [
          {
            "marker": {
              "colorbar": {
                "outlinewidth": 0,
                "ticks": ""
              }
            },
            "type": "scattermapbox"
          }
        ],
        "scatterpolar": [
          {
            "marker": {
              "colorbar": {
                "outlinewidth": 0,
                "ticks": ""
              }
            },
            "type": "scatterpolar"
          }
        ],
        "scatterpolargl": [
          {
            "marker": {
              "colorbar": {
                "outlinewidth": 0,
                "ticks": ""
              }
            },
            "type": "scatterpolargl"
          }
        ],
        "scatterternary": [
          {
            "marker": {
              "colorbar": {
                "outlinewidth": 0,
                "ticks": ""
              }
            },
            "type": "scatterternary"
          }
        ],
        "surface": [
          {
            "colorbar": {
              "outlinewidth": 0,
              "ticks": ""
            },
            "colorscale": [
              [
                0.0,
                "#0d0887"
              ],
              [
                0.1111111111111111,
                "#46039f"
              ],
              [
                0.2222222222222222,
                "#7201a8"
              ],
              [
                0.3333333333333333,
                "#9c179e"
              ],
              [
                0.4444444444444444,
                "#bd3786"
              ],
              [
                0.5555555555555556,
                "#d8576b"
              ],
              [
                0.6666666666666666,
                "#ed7953"
              ],
              [
                0.7777777777777778,
                "#fb9f3a"
              ],
              [
                0.8888888888888888,
                "#fdca26"
              ],
              [
                1.0,
                "#f0f921"
              ]
            ],
            "type": "surface"
          }
        ],
        "table": [
          {
            "cells": {
              "fill": {
                "color": "#EBF0F8"
              },
              "line": {
                "color": "white"
              }
            },
            "header": {
              "fill": {
                "color": "#C8D4E3"
              },
              "line": {
                "color": "white"
              }
            },
            "type": "table"
          }
        ]
      },
      "layout": {
        "annotationdefaults": {
          "arrowcolor": "#2a3f5f",
          "arrowhead": 0,
          "arrowwidth": 1
        },
        "autotypenumbers": "strict",
        "coloraxis": {
          "colorbar": {
            "outlinewidth": 0,
            "ticks": ""
          }
        },
        "colorscale": {
          "diverging": [
            [
              0,
              "#8e0152"
            ],
            [
              0.1,
              "#c51b7d"
            ],
            [
              0.2,
              "#de77ae"
            ],
            [
              0.3,
              "#f1b6da"
            ],
            [
              0.4,
              "#fde0ef"
            ],
            [
              0.5,
              "#f7f7f7"
            ],
            [
              0.6,
              "#e6f5d0"
            ],
            [
              0.7,
              "#b8e186"
            ],
            [
              0.8,
              "#7fbc41"
            ],
            [
              0.9,
              "#4d9221"
            ],
            [
              1,
              "#276419"
            ]
          ],
          "sequential": [
            [
              0.0,
              "#0d0887"
            ],
            [
              0.1111111111111111,
              "#46039f"
            ],
            [
              0.2222222222222222,
              "#7201a8"
            ],
            [
              0.3333333333333333,
              "#9c179e"
            ],
            [
              0.4444444444444444,
              "#bd3786"
            ],
            [
              0.5555555555555556,
              "#d8576b"
            ],
            [
              0.6666666666666666,
              "#ed7953"
            ],
            [
              0.7777777777777778,
              "#fb9f3a"
            ],
            [
              0.8888888888888888,
              "#fdca26"
            ],
            [
              1.0,
              "#f0f921"
            ]
          ],
          "sequentialminus": [
            [
              0.0,
              "#0d0887"
            ],
            [
              0.1111111111111111,
              "#46039f"
            ],
            [
              0.2222222222222222,
              "#7201a8"
            ],
            [
              0.3333333333333333,
              "#9c179e"
            ],
            [
              0.4444444444444444,
              "#bd3786"
            ],
            [
              0.5555555555555556,
              "#d8576b"
            ],
            [
              0.6666666666666666,
              "#ed7953"
            ],
            [
              0.7777777777777778,
              "#fb9f3a"
            ],
            [
              0.8888888888888888,
              "#fdca26"
            ],
            [
              1.0,
              "#f0f921"
            ]
          ]
        },
        "colorway": [
          "#636efa",
          "#EF553B",
          "#00cc96",
          "#ab63fa",
          "#FFA15A",
          "#19d3f3",
          "#FF6692",
          "#B6E880",
          "#FF97FF",
          "#FECB52"
        ],
        "font": {
          "color": "#2a3f5f"
        },
        "geo": {
          "bgcolor": "white",
          "lakecolor": "white",
          "landcolor": "white",
          "showlakes": true,
          "showland": true,
          "subunitcolor": "#C8D4E3"
        },
        "hoverlabel": {
          "align": "left"
        },
        "hovermode": "closest",
        "mapbox": {
          "style": "light"
        },
        "paper_bgcolor": "white",
        "plot_bgcolor": "white",
        "polar": {
          "angularaxis": {
            "gridcolor": "#EBF0F8",
            "linecolor": "#EBF0F8",
            "ticks": ""
          },
          "bgcolor": "white",
          "radialaxis": {
            "gridcolor": "#EBF0F8",
            "linecolor": "#EBF0F8",
            "ticks": ""
          }
        },
        "scene": {
          "xaxis": {
            "backgroundcolor": "white",
            "gridcolor": "#DFE8F3",
            "gridwidth": 2,
            "linecolor": "#EBF0F8",
            "showbackground": true,
            "ticks": "",
            "zerolinecolor": "#EBF0F8"
          },
          "yaxis": {
            "backgroundcolor": "white",
            "gridcolor": "#DFE8F3",
            "gridwidth": 2,
            "linecolor": "#EBF0F8",
            "showbackground": true,
            "ticks": "",
            "zerolinecolor": "#EBF0F8"
          },
          "zaxis": {
            "backgroundcolor": "white",
            "gridcolor": "#DFE8F3",
            "gridwidth": 2,
            "linecolor": "#EBF0F8",
            "showbackground": true,
            "ticks": "",
            "zerolinecolor": "#EBF0F8"
          }
        },
        "shapedefaults": {
          "line": {
            "color": "#2a3f5f"
          }
        },
        "ternary": {
          "aaxis": {
            "gridcolor": "#DFE8F3",
            "linecolor": "#A2B1C6",
            "ticks": ""
          },
          "baxis": {
            "gridcolor": "#DFE8F3",
            "linecolor": "#A2B1C6",
            "ticks": ""
          },
          "bgcolor": "white",
          "caxis": {
            "gridcolor": "#DFE8F3",
            "linecolor": "#A2B1C6",
            "ticks": ""
          }
        },
        "title": {
          "x": 0.05
        },
        "xaxis": {
          "automargin": true,
          "gridcolor": "#EBF0F8",
          "linecolor": "#EBF0F8",
          "ticks": "",
          "title": {
            "standoff": 15
          },
          "zerolinecolor": "#EBF0F8",
          "zerolinewidth": 2
        },
        "yaxis": {
          "automargin": true,
          "gridcolor": "#EBF0F8",
          "linecolor": "#EBF0F8",
          "ticks": "",
          "title": {
            "standoff": 15
          },
          "zerolinecolor": "#EBF0F8",
          "zerolinewidth": 2
        }
      }
    },
    "width": 800,
    "xaxis": {
      "showgrid": false,
      "visible": false,
      "zeroline": false
    },
    "yaxis": {
      "scaleanchor": "x",
      "scaleratio": 1,
      "showgrid": false,
      "visible": false,
      "zeroline": false
    }
  }
}