{
  "data": [
    {
      "hoverinfo": "none",
      "line": {
        "color": "#ff6f6f ",
        "shape": "linear",
        "width": 10.0
      },
      "mode": "lines",
      "textposition": "middle center",
      "type": "scatter",
      "x": [
        0.83827,
        0.942593
      ],
      "y": [
        -0.501021,
        0.30392
      ]
    },
    {
      "hoverinfo": "none",
      "line": {
        "color": "#ff6f6f ",
        "shape": "linear",
        "width": 10.0
      },
      "mode": "lines",
      "textposition": "middle center",
      "type": "scatter",
      "x": [
        0.942593,
        0.83827
      ],
      "y": [
        0.30392,
        -0.501021
      ]
    },
    {
      "hoverinfo": "none",
      "line": {
        "color": "#ff6f6f ",
        "shape": "linear",
        "width": 5.5
      },
      "mode": "lines",
      "textposition": "middle center",
      "type": "scatter",
      "x": [
        0.975317,
        -0.913748
      ],
      "y": [
        -0.341929,
        -0.16306
      ]
    },
    {
      "hoverinfo": "none",
      "line": {
        "color": "#ff6f6f ",
        "shape": "linear",
        "width": 5.5
      },
      "mode": "lines",
      "textposition": "middle center",
      "type": "scatter",
      "x": [
        -0.913748,
        0.975317
      ],
      "y": [
        -0.16306,
        -0.341929
      ]
    },
    {
      "hoverinfo": "none",
      "line": {
        "color": "#ff6f6f ",
        "shape": "linear",
        "width": 5.5
      },
      "mode": "lines",
      "textposition": "middle center",
      "type": "scatter",
      "x": [
        -0.143902,
        0.415029
      ],
      "y": [
        -0.981043,
        0.576914
      ]
    },
    {
      "hoverinfo": "none",
      "line": {
        "color": "#ff6f6f ",
        "shape": "linear",
        "width": 5.5
      },
      "mode": "lines",
      "textposition": "middle center",
      "type": "scatter",
      "x": [
        0.415029,
        -0.143902
      ],
      "y": [
        0.576914,
        -0.981043
      ]
    },
    {
      "hoverinfo": "none",
      "line": {
        "color": "#ff6f6f ",
        "shape": "linear",
        "width": 10.0
      },
      "mode": "lines",
      "textposition": "middle center",
      "type": "scatter",
      "x": [
        -0.266525,
        0.415029
      ],
      "y": [
        -0.98251,
        0.576914
      ]
    },
    {
      "hoverinfo": "none",
      "line": {
        "color": "#ff6f6f ",
        "shape": "linear",
        "width": 10.0
      },
      "mode": "lines",
      "textposition": "middle center",
      "type": "scatter",
      "x": [
        0.415029,
        -0.266525
      ],
      "y": [
        0.576914,
        -0.98251
      ]
    },
    {
      "hoverinfo": "none",
      "line": {
        "color": "#ff6f6f ",
        "shape": "linear",
        "width": 5.5
      },
      "mode": "lines",
      "textposition": "middle center",
      "type": "scatter",
      "x": [
        0.341685,
        -0.855681
      ],
      "y": [
        0.762961,
        -0.587328
      ]
    },
    {
      "hoverinfo": "none",
      "line": {
        "color": "#ff6f6f ",
        "shape": "linear",
        "width": 5.5
      },
      "mode": "lines",
      "textposition": "middle center",
      "type": "scatter",
      "x": [
        -0.855681,
        0.341685
      ],
      "y": [
        -0.587328,
        0.762961
      ]
    },
    {
      "hoverinfo": "none",
      "line": {
        "color": "#ff6f6f ",
        "shape": "linear",
        "width": 5.5
      },
      "mode": "lines",
      "textposition": "middle center",
      "type": "scatter",
      "x": [
        0.622389,
        -0.773028
      ],
      "y": [
        0.496683,
        -0.60745
      ]
    },
    {
      "hoverinfo": "none",
      "line": {
        "color": "#ff6f6f ",
        "shape": "linear",
        "width": 5.5
      },
      "mode": "lines",
      "textposition": "middle center",
      "type": "scatter",
      "x": [
        -0.773028,
        0.622389
      ],
      "y": [
        -0.60745,
        0.496683
      ]
    },
    {
      "hoverinfo": "none",
      "line": {
        "color": "#ff6f6f ",
        "shape": "linear",
        "width": 10.0
      },
      "mode": "lines",
      "textposition": "middle center",
      "type": "scatter",
      "x": [
        0.080994,
        -0.374323
      ],
      "y": [
        0.898939,
        -0.928417
      ]
    },
    {
      "hoverinfo": "none",
      "line": {
        "color": "#ff6f6f ",
        "shape": "linear",
        "width": 10.0
      },
      "mode": "lines",
      "textposition": "middle center",
      "type": "scatter",
      "x": [
        -0.374323,
        0.080994
      ],
      "y": [
        -0.928417,
        0.898939
      ]
    },
    {
      "hoverinfo": "none",
      "line": {
        "color": "#ff6f6f ",
        "shape": "linear",
        "width": 5.5
      },
      "mode": "lines",
      "textposition": "middle center",
      "type": "scatter",
      "x": [
        0.876156,
        0.106863
      ],
      "y": [
        -0.21291,
        -0.955752
      ]
    },
    {
      "hoverinfo": "none",
      "line": {
        "color": "#ff6f6f ",
        "shape": "linear",
        "width": 5.5
      },
      "mode": "lines",
      "textposition": "middle center",
      "type": "scatter",
      "x": [
        0.106863,
        0.876156
      ],
      "y": [
        -0.955752,
        -0.21291
      ]
    },
    {
      "hoverinfo": "none",
      "line": {
        "color": "#ff6f6f ",
        "shape": "linear",
        "width": 10.0
      },
      "mode": "lines",
      "textposition": "middle center",
      "type": "scatter",
      "x": [
        -0.624109,
        0.671673
      ],
      "y": [
        -0.868528,
        -0.697631
      ]
    },
    {
      "hoverinfo": "none",
      "line": {
        "color": "#ff6f6f ",
        "shape": "linear",
        "width": 10.0
      },
      "mode": "lines",
      "textposition": "middle center",
      "type": "scatter",
      "x": [
        0.671673,
        -0.624109
      ],
      "y": [
        -0.697631,
        -0.868528
      ]
    },
    {
      "hoverinfo": "none",
      "line": {
        "color": "#ff6f6f ",
        "shape": "linear",
        "width": 5.5
      },
      "mode": "lines",
      "textposition": "middle center",
      "type": "scatter",
      "x": [
        -0.84454,
        -0.361039
      ],
      "y": [
        0.575939,
        0.847846
      ]
    },
    {
      "hoverinfo": "none",
      "line": {
        "color": "#ff6f6f ",
        "shape": "linear",
        "width": 5.5
      },
      "mode": "lines",
      "textposition": "middle center",
      "type": "scatter",
      "x": [
        -0.361039,
        -0.84454
      ],
      "y": [
        0.847846,
        0.575939
      ]
    },
    {
      "hoverinfo": "none",
      "line": {
        "color": "#ff6f6f ",
        "shape": "linear",
        "width": 5.5
      },
      "mode": "lines",
      "textposition": "middle center",
      "type": "scatter",
      "x": [
        -0.84454,
        0.764309
      ],
      "y": [
        0.575939,
        0.238217
      ]
    },
    {
      "hoverinfo": "none",
      "line": {
        "color": "#ff6f6f ",
        "shape": "linear",
        "width": 5.5
      },
      "mode": "lines",
      "textposition": "middle center",
      "type": "scatter",
      "x": [
        0.764309,
        -0.84454
      ],
      "y": [
        0.238217,
        0.575939
      ]
    },
    {
      "hoverinfo": "none",
      "line": {
        "color": "#ff6f6f ",
        "shape": "linear",
        "width": 5.5
      },
      "mode": "lines",
      "textposition": "middle center",
      "type": "scatter",
      "x": [
        0.404095,
        0.385726
      ],
      "y": [
        0.914349,
        -0.740438
      ]
    },
    {
      "hoverinfo": "none",
      "line": {
        "color": "#ff6f6f ",
        "shape": "linear",
        "width": 5.5
      },
      "mode": "lines",
      "textposition": "middle center",
      "type": "scatter",
      "x": [
        0.385726,
        0.404095
      ],
      "y": [
        -0.740438,
        0.914349
      ]
    },
    {
      "hoverinfo": "none",
      "line": {
        "color": "#ff6f6f ",
        "shape": "linear",
        "width": 5.5
      },
      "mode": "lines",
      "textposition": "middle center",
      "type": "scatter",
      "x": [
        0.404095,
        -0.646827
      ],
      "y": [
        0.914349,
        0.754862
      ]
    },
    {
      "hoverinfo": "none",
      "line": {
        "color": "#ff6f6f ",
        "shape": "linear",
        "width": 5.5
      },
      "mode": "lines",
      "textposition": "middle center",
      "type": "scatter",
      "x": [
        -0.646827,
        0.404095
      ],
      "y": [
        0.754862,
        0.914349
      ]
    },
    {
      "hoverinfo": "none",
      "line": {
        "color": "#ff6f6f ",
        "shape": "linear",
        "width": 5.5
      },
      "mode": "lines",
      "textposition": "middle center",
      "type": "scatter",
      "x": [
        0.404095,
        0.723258
      ],
      "y": [
        0.914349,
        -0.561525
      ]
    },
    {
      "hoverinfo": "none",
      "line": {
        "color": "#ff6f6f ",
        "shape": "linear",
        "width": 5.5
      },
      "mode": "lines",
      "textposition": "middle center",
      "type": "scatter",
      "x": [
        0.723258,
        0.404095
      ],
      "y": [
        -0.561525,
        0.914349
      ]
    },
    {
      "hoverinfo": "none",
      "line": {
        "color": "#ff6f6f ",
        "shape": "linear",
        "width": 5.5
      },
      "mode": "lines",
      "textposition": "middle center",
      "type": "scatter",
      "x": [
        -0.646827,
        0.723258
      ],
      "y": [
        0.754862,
        -0.561525
      ]
    },
    {
      "hoverinfo": "none",
      "line": {
        "color": "#ff6f6f ",
        "shape": "linear",
        "width": 5.5
      },
      "mode": "lines",
      "textposition": "middle center",
      "type": "scatter",
      "x": [
        0.723258,
        -0.646827
      ],
      "y": [
        -0.561525,
        0.754862
      ]
    },
    {
      "hoverinfo": "none",
      "line": {
        "color": "#ff6f6f ",
        "shape": "linear",
        "width": 5.5
      },
      "mode": "lines",
      "textposition": "middle center",
      "type": "scatter",
      "x": [
        0.723258,
        0.570097
      ],
      "y": [
        -0.561525,
        -0.53472
      ]
    },
    {
      "hoverinfo": "none",
      "line": {
        "color": "#ff6f6f ",
        "shape": "linear",
        "width": 5.5
      },
      "mode": "lines",
      "textposition": "middle center",
      "type": "scatter",
      "x": [
        0.570097,
        0.723258
      ],
      "y": [
        -0.53472,
        -0.561525
      ]
    },
    {
      "hoverinfo": "none",
      "line": {
        "color": "#ff6f6f ",
        "shape": "linear",
        "width": 5.5
      },
      "mode": "lines",
      "textposition": "middle center",
      "type": "scatter",
      "x": [
        -0.877232,
        0.810677
      ],
      "y": [
        -0.356665,
        0.567857
      ]
    },
    {
      "hoverinfo": "none",
      "line": {
        "color": "#ff6f6f ",
        "shape": "linear",
        "width": 5.5
      },
      "mode": "lines",
      "textposition": "middle center",
      "type": "scatter",
      "x": [
        0.810677,
        -0.877232
      ],
      "y": [
        0.567857,
        -0.356665
      ]
    },
    {
      "hoverinfo": "none",
      "line": {
        "color": "#ff6f6f ",
        "shape": "linear",
        "width": 5.5
      },
      "mode": "lines",
      "textposition": "middle center",
      "type": "scatter",
      "x": [
        -0.48886,
        -0.772902
      ],
      "y": [
        0.842036,
        0.371652
      ]
    },
    {
      "hoverinfo": "none",
      "line": {
        "color": "#ff6f6f ",
        "shape": "linear",
        "width": 5.5
      },
      "mode": "lines",
      "textposition": "middle center",
      "type": "scatter",
      "x": [
        -0.772902,
        -0.48886
      ],
      "y": [
        0.371652,
        0.842036
      ]
    },
    {
      "hoverinfo": "none",
      "line": {
        "color": "#ff6f6f ",
        "shape": "linear",
        "width": 10.0
      },
      "mode": "lines",
      "textposition": "middle center",
      "type": "scatter",
      "x": [
        -0.89387,
        -0.338042
      ],
      "y": [
        -0.058716,
        0.735214
      ]
    },
    {
      "hoverinfo": "none",
      "line": {
        "color": "#ff6f6f ",
        "shape": "linear",
        "width": 10.0
      },
      "mode": "lines",
      "textposition": "middle center",
      "type": "scatter",
      "x": [
        -0.338042,
        -0.89387
      ],
      "y": [
        0.735214,
        -0.058716
      ]
    },
    {
      "hoverinfo": "none",
      "line": {
        "color": "#ff6f6f ",
        "shape": "linear",
        "width": 5.5
      },
      "mode": "lines",
      "textposition": "middle center",
      "type": "scatter",
      "x": [
        -0.89387,
        0.671673
      ],
      "y": [
        -0.058716,
        -0.697631
      ]
    },
    {
      "hoverinfo": "none",
      "line": {
        "color": "#ff6f6f ",
        "shape": "linear",
        "width": 5.5
      },
      "mode": "lines",
      "textposition": "middle center",
      "type": "scatter",
      "x": [
        0.671673,
        -0.89387
      ],
      "y": [
        -0.697631,
        -0.058716
      ]
    },
    {
      "hoverinfo": "none",
      "line": {
        "color": "#ff6f6f ",
        "shape": "linear",
        "width": 5.5
      },
      "mode": "lines",
      "textposition": "middle center",
      "type": "scatter",
      "x": [
        -0.89387,
        -0.361039
      ],
      "y": [
        -0.058716,
        0.847846
      ]
    },
    {
      "hoverinfo": "none",
      "line": {
        "color": "#ff6f6f ",
        "shape": "linear",
        "width": 5.5
      },
      "mode": "lines",
      "textposition": "middle center",
      "type": "scatter",
      "x": [
        -0.361039,
        -0.89387
      ],
      "y": [
        0.847846,
        -0.058716
      ]
    },
    {
      "hoverinfo": "none",
      "line": {
        "color": "#ff6f6f ",
        "shape": "linear",
        "width": 5.5
      },
      "mode": "lines",
      "textposition": "middle center",
      "type": "scatter",
      "x": [
        -0.338042,
        0.176961
      ],
      "y": [
        0.735214,
        -0.847504
      ]
    },
    {
      "hoverinfo": "none",
      "line": {
        "color": "#ff6f6f ",
        "shape": "linear",
        "width": 5.5
      },
      "mode": "lines",
      "textposition": "middle center",
      "type": "scatter",
      "x": [
        0.176961,
        -0.338042
      ],
      "y": [
        -0.847504,
        0.735214
      ]
    },
    {
      "hoverinfo": "none",
      "line": {
        "color": "#ff6f6f ",
        "shape": "linear",
        "width": 5.5
      },
      "mode": "lines",
      "textposition": "middle center",
      "type": "scatter",
      "x": [
        -0.338042,
        0.764309
      ],
      "y": [
        0.735214,
        0.238217
      ]
    },
    {
      "hoverinfo": "none",
      "line": {
        "color": "#ff6f6f ",
        "shape": "linear",
        "width": 5.5
      },
      "mode": "lines",
      "textposition": "middle center",
      "type": "scatter",
      "x": [
        0.764309,
        -0.338042
      ],
      "y": [
        0.238217,
        0.735214
      ]
    },
    {
      "hoverinfo": "none",
      "line": {
        "color": "#ff6f6f ",
        "shape": "linear",
        "width": 5.5
      },
      "mode": "lines",
      "textposition": "middle center",
      "type": "scatter",
      "x": [
        -0.814584,
        0.685934
      ],
      "y": [
        0.489171,
        -0.80944
      ]
    },
    {
      "hoverinfo": "none",
      "line": {
        "color": "#ff6f6f ",
        "shape": "linear",
        "width": 5.5
      },
      "mode": "lines",
      "textposition": "middle center",
      "type": "scatter",
      "x": [
        0.685934,
        -0.814584
      ],
      "y": [
        -0.80944,
        0.489171
      ]
    },
    {
      "hoverinfo": "text",
      "hovertext": [
        "<b>ADEL</b><br>Sensory neuron (mechanosensory)",
        "<b>ADER</b><br>Sensory neuron (mechanosensory)",
        "<b>ADFL</b><br>Sensory neuron (amphid)<br>Conns in: <b>ADFR</b>: 2<br>Conns out: <b>ADFR</b>: 2",
        "<b>ADFR</b><br>Sensory neuron (amphid)<br>Conns in: <b>ADFL</b>: 2<br>Conns out: <b>ADFL</b>: 2",
        "<b>ADLL</b><br>Sensory neuron (amphid, nociceptive)<br>Conns in: <b>ADLR</b>: 1<br>Conns out: <b>ADLR</b>: 1",
        "<b>ADLR</b><br>Sensory neuron (amphid, nociceptive)<br>Conns in: <b>ADLL</b>: 1<br>Conns out: <b>ADLL</b>: 1",
        "<b>AFDL</b><br>Sensory neuron (amphid)",
        "<b>AFDR</b><br>Sensory neuron (amphid)",
        "<b>ALML</b><br>Sensory neuron (mechanosensory)<br>Conns in: <b>AVM</b>: 1<br>Conns out: <b>AVM</b>: 1",
        "<b>ALMR</b><br>Sensory neuron (mechanosensory)<br>Conns in: <b>AVM</b>: 2<br>Conns out: <b>AVM</b>: 2",
        "<b>ALNL</b><br>Sensory neuron (touch)",
        "<b>ALNR</b><br>Sensory neuron (touch)",
        "<b>AQR</b><br>Sensory neuron (touch)",
        "<b>ASEL</b><br>Sensory neuron (amphid)",
        "<b>ASER</b><br>Sensory neuron (amphid)",
        "<b>ASGL</b><br>Sensory neuron (amphid)",
        "<b>ASGR</b><br>Sensory neuron (amphid)",
        "<b>ASHL</b><br>Sensory neuron (amphid, nociceptive)",
        "<b>ASHR</b><br>Sensory neuron (amphid, nociceptive)",
        "<b>ASIL</b><br>Sensory neuron (amphid)<br>Conns in: <b>ASIR</b>: 1<br>Conns out: <b>ASIR</b>: 1",
        "<b>ASIR</b><br>Sensory neuron (amphid)<br>Conns in: <b>ASIL</b>: 1<br>Conns out: <b>ASIL</b>: 1",
        "<b>ASJL</b><br>Sensory neuron (amphid)",
        "<b>ASJR</b><br>Sensory neuron (amphid)",
        "<b>ASKL</b><br>Sensory neuron (amphid)<br>Conns in: <b>AWCL</b>: 1<br>Conns out: <b>AWCL</b>: 1",
        "<b>ASKR</b><br>Sensory neuron (amphid)",
        "<b>AVM</b><br>Sensory neuron (mechanosensory)<br>Conns in: <b>ALMR</b>: 2, <b>ALML</b>: 1<br>Conns out: <b>ALMR</b>: 2, <b>ALML</b>: 1",
        "<b>AWAL</b><br>Sensory neuron (amphid)",
        "<b>AWAR</b><br>Sensory neuron (amphid)",
        "<b>AWBL</b><br>Sensory neuron (amphid)<br>Conns in: <b>AWBR</b>: 2<br>Conns out: <b>AWBR</b>: 2",
        "<b>AWBR</b><br>Sensory neuron (amphid)<br>Conns in: <b>AWBL</b>: 2<br>Conns out: <b>AWBL</b>: 2",
        "<b>AWCL</b><br>Sensory neuron (amphid)<br>Conns in: <b>ASKL</b>: 1<br>Conns out: <b>ASKL</b>: 1",
        "<b>AWCR</b><br>Sensory neuron (amphid)",
        "<b>BAGL</b><br>Sensory neuron (O2, CO2, social signals, touch)<br>Conns in: <b>BAGR</b>: 1<br>Conns out: <b>BAGR</b>: 1",
        "<b>BAGR</b><br>Sensory neuron (O2, CO2, social signals, touch)<br>Conns in: <b>BAGL</b>: 1<br>Conns out: <b>BAGL</b>: 1",
        "<b>CEPDL</b><br>Sensory neuron (cephalic)<br>Conns in: <b>OLQDL</b>: 2<br>Conns out: <b>OLQDL</b>: 2",
        "<b>CEPDR</b><br>Sensory neuron (cephalic)",
        "<b>CEPVL</b><br>Sensory neuron (cephalic)",
        "<b>CEPVR</b><br>Sensory neuron (cephalic)",
        "<b>DVA</b><br>Sensory neuron (mechanosensory)<br>Conns in: <b>OLQVL</b>: 1, <b>OLQVR</b>: 1<br>Conns out: <b>OLQVL</b>: 1, <b>OLQVR</b>: 1",
        "<b>FLPL</b><br>Sensory neuron (mechanosensory)",
        "<b>FLPR</b><br>Sensory neuron (mechanosensory)",
        "<b>IL1DL</b><br>Sensory neuron (cephalic)<br>Conns in: <b>IL1DR</b>: 1, <b>IL1L</b>: 1, <b>IL1VL</b>: 1<br>Conns out: <b>IL1DR</b>: 1, <b>IL1L</b>: 1, <b>IL1VL</b>: 1",
        "<b>IL1DR</b><br>Sensory neuron (cephalic)<br>Conns in: <b>IL1DL</b>: 1<br>Conns out: <b>IL1DL</b>: 1",
        "<b>IL1L</b><br>Sensory neuron (cephalic)<br>Conns in: <b>IL1DL</b>: 1, <b>IL1VL</b>: 1<br>Conns out: <b>IL1DL</b>: 1, <b>IL1VL</b>: 1",
        "<b>IL1R</b><br>Sensory neuron (cephalic)",
        "<b>IL1VL</b><br>Sensory neuron (cephalic)<br>Conns in: <b>IL1DL</b>: 1, <b>IL1L</b>: 1, <b>IL1VR</b>: 1<br>Conns out: <b>IL1DL</b>: 1, <b>IL1L</b>: 1, <b>IL1VR</b>: 1",
        "<b>IL1VR</b><br>Sensory neuron (cephalic)<br>Conns in: <b>IL1VL</b>: 1<br>Conns out: <b>IL1VL</b>: 1",
        "<b>IL2DL</b><br>Sensory neuron (cephalic)",
        "<b>IL2DR</b><br>Sensory neuron (cephalic)",
        "<b>IL2L</b><br>Sensory neuron (cephalic)<br>Conns in: <b>URXL</b>: 1<br>Conns out: <b>URXL</b>: 1",
        "<b>IL2R</b><br>Sensory neuron (cephalic)<br>Conns in: <b>URXR</b>: 1<br>Conns out: <b>URXR</b>: 1",
        "<b>IL2VL</b><br>Sensory neuron (cephalic)",
        "<b>IL2VR</b><br>Sensory neuron (cephalic)",
        "<b>OLLL</b><br>Sensory neuron (cephalic)<br>Conns in: <b>OLLR</b>: 2, <b>OLQDL</b>: 1, <b>OLQVL</b>: 1<br>Conns out: <b>OLLR</b>: 2, <b>OLQDL</b>: 1, <b>OLQVL</b>: 1",
        "<b>OLLR</b><br>Sensory neuron (cephalic)<br>Conns in: <b>OLLL</b>: 2, <b>OLQDR</b>: 1, <b>OLQVR</b>: 1<br>Conns out: <b>OLLL</b>: 2, <b>OLQDR</b>: 1, <b>OLQVR</b>: 1",
        "<b>OLQDL</b><br>Sensory neuron (cephalic)<br>Conns in: <b>CEPDL</b>: 2, <b>OLLL</b>: 1<br>Conns out: <b>CEPDL</b>: 2, <b>OLLL</b>: 1",
        "<b>OLQDR</b><br>Sensory neuron (cephalic)<br>Conns in: <b>OLLR</b>: 1<br>Conns out: <b>OLLR</b>: 1",
        "<b>OLQVL</b><br>Sensory neuron (cephalic)<br>Conns in: <b>DVA</b>: 1, <b>OLLL</b>: 1<br>Conns out: <b>DVA</b>: 1, <b>OLLL</b>: 1",
        "<b>OLQVR</b><br>Sensory neuron (cephalic)<br>Conns in: <b>DVA</b>: 1, <b>OLLR</b>: 1<br>Conns out: <b>DVA</b>: 1, <b>OLLR</b>: 1",
        "<b>PDEL</b><br>Sensory neuron (mechanosensory)",
        "<b>PDER</b><br>Sensory neuron (mechanosensory)",
        "<b>PHAL</b><br>Sensory neuron (phasmid)",
        "<b>PHAR</b><br>Sensory neuron (phasmid)",
        "<b>PHBL</b><br>Sensory neuron (phasmid)",
        "<b>PHBR</b><br>Sensory neuron (phasmid)",
        "<b>PHCL</b><br>Sensory neuron (phasmid)",
        "<b>PHCR</b><br>Sensory neuron (phasmid)",
        "<b>PLML</b><br>Sensory neuron (mechanosensory)",
        "<b>PLMR</b><br>Sensory neuron (mechanosensory)",
        "<b>PLNL</b><br>Sensory neuron (touch)",
        "<b>PLNR</b><br>Sensory neuron (touch)",
        "<b>PQR</b><br>Sensory neuron (touch)",
        "<b>PVDL</b><br>Sensory neuron (mechanosensory)",
        "<b>PVDR</b><br>Sensory neuron (mechanosensory)",
        "<b>PVM</b><br>Sensory neuron (mechanosensory)",
        "<b>SDQL</b><br>Sensory neuron (touch)<br>Conns in: <b>SDQR</b>: 1<br>Conns out: <b>SDQR</b>: 1",
        "<b>SDQR</b><br>Sensory neuron (touch)<br>Conns in: <b>SDQL</b>: 1<br>Conns out: <b>SDQL</b>: 1",
        "<b>URXL</b><br>Sensory neuron (O2, CO2, social signals, touch)<br>Conns in: <b>IL2L</b>: 1<br>Conns out: <b>IL2L</b>: 1",
        "<b>URXR</b><br>Sensory neuron (O2, CO2, social signals, touch)<br>Conns in: <b>IL2R</b>: 1<br>Conns out: <b>IL2R</b>: 1",
        "<b>URYDL</b><br>Sensory neuron (cephalic)",
        "<b>URYDR</b><br>Sensory neuron (cephalic)",
        "<b>URYVL</b><br>Sensory neuron (cephalic)",
        "<b>URYVR</b><br>Sensory neuron (cephalic)"
      ],
      "marker": {
        "color": [
          "#ff66cc",
          "#ff66cc",
          "#ff66cc",
          "#ff66cc",
          "#ff66cc",
          "#ff66cc",
          "#ff66cc",
          "#ff66cc",
          "#ff66cc",
          "#ff66cc",
          "#ff66cc",
          "#ff66cc",
          "#ff66cc",
          "#ff66cc",
          "#ff66cc",
          "#ff66cc",
          "#ff66cc",
          "#ff66cc",
          "#ff66cc",
          "#ff66cc",
          "#ff66cc",
          "#ff66cc",
          "#ff66cc",
          "#ff66cc",
          "#ff66cc",
          "#ff66cc",
          "#ff66cc",
          "#ff66cc",
          "#ff66cc",
          "#ff66cc",
          "#ff66cc",
          "#ff66cc",
          "#ff66cc",
          "#ff66cc",
          "#ff66cc",
          "#ff66cc",
          "#ff66cc",
          "#ff66cc",
          "#ff66cc",
          "#ff66cc",
          "#ff66cc",
          "#ff66cc",
          "#ff66cc",
          "#ff66cc",
          "#ff66cc",
          "#ff66cc",
          "#ff66cc",
          "#ff66cc",
          "#ff66cc",
          "#ff66cc",
          "#ff66cc",
          "#ff66cc",
          "#ff66cc",
          "#ff66cc",
          "#ff66cc",
          "#ff66cc",
          "#ff66cc",
          "#ff66cc",
          "#ff66cc",
          "#ff66cc",
          "#ff66cc",
          "#ff66cc",
          "#ff66cc",
          "#ff66cc",
          "#ff66cc",
          "#ff66cc",
          "#ff66cc",
          "#ff66cc",
          "#ff66cc",
          "#ff66cc",
          "#ff66cc",
          "#ff66cc",
          "#ff66cc",
          "#ff66cc",
          "#ff66cc",
          "#ff66cc",
          "#ff66cc",
          "#ff66cc",
          "#ff66cc",
          "#ff66cc",
          "#ff66cc",
          "#ff66cc",
          "#ff66cc"
        ],
        "colorbar": {
          "thickness": 15,
          "title": {
            "text": "Node Connections"
          },
          "xanchor": "left"
        },
        "colorscale": [
          [
            0.0,
            "rgb(255,255,217)"
          ],
          [
            0.125,
            "rgb(237,248,177)"
          ],
          [
            0.25,
            "rgb(199,233,180)"
          ],
          [
            0.375,
            "rgb(127,205,187)"
          ],
          [
            0.5,
            "rgb(65,182,196)"
          ],
          [
            0.625,
            "rgb(29,145,192)"
          ],
          [
            0.75,
            "rgb(34,94,168)"
          ],
          [
            0.875,
            "rgb(37,52,148)"
          ],
          [
            1.0,
            "rgb(8,29,88)"
          ]
        ],
        "line": {
          "width": 1
        },
        "reversescale": true,
        "showscale": false,
        "size": [
          15.0,
          15.0,
          15.0,
          15.0,
          15.0,
          15.0,
          15.0,
          15.0,
          15.0,
          15.0,
          15.0,
          15.0,
          15.0,
          15.0,
          15.0,
          15.0,
          15.0,
          15.0,
          15.0,
          15.0,
          15.0,
          15.0,
          15.0,
          15.0,
          15.0,
          15.0,
          15.0,
          15.0,
          15.0,
          15.0,
          15.0,
          15.0,
          15.0,
          15.0,
          15.0,
          15.0,
          15.0,
          15.0,
          15.0,
          15.0,
          15.0,
          15.0,
          15.0,
          15.0,
          15.0,
          15.0,
          15.0,
          15.0,
          15.0,
          15.0,
          15.0,
          15.0,
          15.0,
          15.0,
          15.0,
          15.0,
          15.0,
          15.0,
          15.0,
          15.0,
          15.0,
          15.0,
          15.0,
          15.0,
          15.0,
          15.0,
          15.0,
          15.0,
          15.0,
          15.0,
          15.0,
          15.0,
          15.0,
          15.0,
          15.0,
          15.0,
          15.0,
          15.0,
          15.0,
          15.0,
          15.0,
          15.0,
          15.0
        ],
        "symbol": [
          "circle",
          "circle",
          "circle",
          "circle",
          "circle",
          "circle",
          "circle",
          "circle",
          "circle",
          "circle",
          "circle",
          "circle",
          "circle",
          "circle",
          "circle",
          "circle",
          "circle",
          "circle",
          "circle",
          "circle",
          "circle",
          "circle",
          "circle",
          "circle",
          "circle",
          "circle",
          "circle",
          "circle",
          "circle",
          "circle",
          "circle",
          "circle",
          "circle",
          "circle",
          "circle",
          "circle",
          "circle",
          "circle",
          "circle",
          "circle",
          "circle",
          "circle",
          "circle",
          "circle",
          "circle",
          "circle",
          "circle",
          "circle",
          "circle",
          "circle",
          "circle",
          "circle",
          "circle",
          "circle",
          "circle",
          "circle",
          "circle",
          "circle",
          "circle",
          "circle",
          "circle",
          "circle",
          "circle",
          "circle",
          "circle",
          "circle",
          "circle",
          "circle",
          "circle",
          "circle",
          "circle",
          "circle",
          "circle",
          "circle",
          "circle",
          "circle",
          "circle",
          "circle",
          "circle",
          "circle",
          "circle",
          "circle",
          "circle"
        ]
      },
      "mode": "markers",
      "opacity": 1,
      "text": [
        "<span style=\"color:#000000;font-size:1.0em\"><b>ADEL</b></span>",
        "<span style=\"color:#000000;font-size:1.0em\"><b>ADER</b></span>",
        "<span style=\"color:#000000;font-size:1.0em\"><b>ADFL</b></span>",
        "<span style=\"color:#000000;font-size:1.0em\"><b>ADFR</b></span>",
        "<span style=\"color:#000000;font-size:1.0em\"><b>ADLL</b></span>",
        "<span style=\"color:#000000;font-size:1.0em\"><b>ADLR</b></span>",
        "<span style=\"color:#000000;font-size:1.0em\"><b>AFDL</b></span>",
        "<span style=\"color:#000000;font-size:1.0em\"><b>AFDR</b></span>",
        "<span style=\"color:#000000;font-size:1.0em\"><b>ALML</b></span>",
        "<span style=\"color:#000000;font-size:1.0em\"><b>ALMR</b></span>",
        "<span style=\"color:#000000;font-size:1.0em\"><b>ALNL</b></span>",
        "<span style=\"color:#000000;font-size:1.0em\"><b>ALNR</b></span>",
        "<span style=\"color:#000000;font-size:1.0em\"><b>AQR</b></span>",
        "<span style=\"color:#000000;font-size:1.0em\"><b>ASEL</b></span>",
        "<span style=\"color:#000000;font-size:1.0em\"><b>ASER</b></span>",
        "<span style=\"color:#000000;font-size:1.0em\"><b>ASGL</b></span>",
        "<span style=\"color:#000000;font-size:1.0em\"><b>ASGR</b></span>",
        "<span style=\"color:#000000;font-size:1.0em\"><b>ASHL</b></span>",
        "<span style=\"color:#000000;font-size:1.0em\"><b>ASHR</b></span>",
        "<span style=\"color:#000000;font-size:1.0em\"><b>ASIL</b></span>",
        "<span style=\"color:#000000;font-size:1.0em\"><b>ASIR</b></span>",
        "<span style=\"color:#000000;font-size:1.0em\"><b>ASJL</b></span>",
        "<span style=\"color:#000000;font-size:1.0em\"><b>ASJR</b></span>",
        "<span style=\"color:#000000;font-size:1.0em\"><b>ASKL</b></span>",
        "<span style=\"color:#000000;font-size:1.0em\"><b>ASKR</b></span>",
        "<span style=\"color:#000000;font-size:1.0em\"><b>AVM</b></span>",
        "<span style=\"color:#000000;font-size:1.0em\"><b>AWAL</b></span>",
        "<span style=\"color:#000000;font-size:1.0em\"><b>AWAR</b></span>",
        "<span style=\"color:#000000;font-size:1.0em\"><b>AWBL</b></span>",
        "<span style=\"color:#000000;font-size:1.0em\"><b>AWBR</b></span>",
        "<span style=\"color:#000000;font-size:1.0em\"><b>AWCL</b></span>",
        "<span style=\"color:#000000;font-size:1.0em\"><b>AWCR</b></span>",
        "<span style=\"color:#000000;font-size:1.0em\"><b>BAGL</b></span>",
        "<span style=\"color:#000000;font-size:1.0em\"><b>BAGR</b></span>",
        "<span style=\"color:#000000;font-size:1.0em\"><b>CEPDL</b></span>",
        "<span style=\"color:#000000;font-size:1.0em\"><b>CEPDR</b></span>",
        "<span style=\"color:#000000;font-size:1.0em\"><b>CEPVL</b></span>",
        "<span style=\"color:#000000;font-size:1.0em\"><b>CEPVR</b></span>",
        "<span style=\"color:#000000;font-size:1.0em\"><b>DVA</b></span>",
        "<span style=\"color:#000000;font-size:1.0em\"><b>FLPL</b></span>",
        "<span style=\"color:#000000;font-size:1.0em\"><b>FLPR</b></span>",
        "<span style=\"color:#000000;font-size:1.0em\"><b>IL1DL</b></span>",
        "<span style=\"color:#000000;font-size:1.0em\"><b>IL1DR</b></span>",
        "<span style=\"color:#000000;font-size:1.0em\"><b>IL1L</b></span>",
        "<span style=\"color:#000000;font-size:1.0em\"><b>IL1R</b></span>",
        "<span style=\"color:#000000;font-size:1.0em\"><b>IL1VL</b></span>",
        "<span style=\"color:#000000;font-size:1.0em\"><b>IL1VR</b></span>",
        "<span style=\"color:#000000;font-size:1.0em\"><b>IL2DL</b></span>",
        "<span style=\"color:#000000;font-size:1.0em\"><b>IL2DR</b></span>",
        "<span style=\"color:#000000;font-size:1.0em\"><b>IL2L</b></span>",
        "<span style=\"color:#000000;font-size:1.0em\"><b>IL2R</b></span>",
        "<span style=\"color:#000000;font-size:1.0em\"><b>IL2VL</b></span>",
        "<span style=\"color:#000000;font-size:1.0em\"><b>IL2VR</b></span>",
        "<span style=\"color:#000000;font-size:1.0em\"><b>OLLL</b></span>",
        "<span style=\"color:#000000;font-size:1.0em\"><b>OLLR</b></span>",
        "<span style=\"color:#000000;font-size:1.0em\"><b>OLQDL</b></span>",
        "<span style=\"color:#000000;font-size:1.0em\"><b>OLQDR</b></span>",
        "<span style=\"color:#000000;font-size:1.0em\"><b>OLQVL</b></span>",
        "<span style=\"color:#000000;font-size:1.0em\"><b>OLQVR</b></span>",
        "<span style=\"color:#000000;font-size:1.0em\"><b>PDEL</b></span>",
        "<span style=\"color:#000000;font-size:1.0em\"><b>PDER</b></span>",
        "<span style=\"color:#000000;font-size:1.0em\"><b>PHAL</b></span>",
        "<span style=\"color:#000000;font-size:1.0em\"><b>PHAR</b></span>",
        "<span style=\"color:#000000;font-size:1.0em\"><b>PHBL</b></span>",
        "<span style=\"color:#000000;font-size:1.0em\"><b>PHBR</b></span>",
        "<span style=\"color:#000000;font-size:1.0em\"><b>PHCL</b></span>",
        "<span style=\"color:#000000;font-size:1.0em\"><b>PHCR</b></span>",
        "<span style=\"color:#000000;font-size:1.0em\"><b>PLML</b></span>",
        "<span style=\"color:#000000;font-size:1.0em\"><b>PLMR</b></span>",
        "<span style=\"color:#000000;font-size:1.0em\"><b>PLNL</b></span>",
        "<span style=\"color:#000000;font-size:1.0em\"><b>PLNR</b></span>",
        "<span style=\"color:#000000;font-size:1.0em\"><b>PQR</b></span>",
        "<span style=\"color:#000000;font-size:1.0em\"><b>PVDL</b></span>",
        "<span style=\"color:#000000;font-size:1.0em\"><b>PVDR</b></span>",
        "<span style=\"color:#000000;font-size:1.0em\"><b>PVM</b></span>",
        "<span style=\"color:#000000;font-size:1.0em\"><b>SDQL</b></span>",
        "<span style=\"color:#000000;font-size:1.0em\"><b>SDQR</b></span>",
        "<span style=\"color:#000000;font-size:1.0em\"><b>URXL</b></span>",
        "<span style=\"color:#000000;font-size:1.0em\"><b>URXR</b></span>",
        "<span style=\"color:#000000;font-size:1.0em\"><b>URYDL</b></span>",
        "<span style=\"color:#000000;font-size:1.0em\"><b>URYDR</b></span>",
        "<span style=\"color:#000000;font-size:1.0em\"><b>URYVL</b></span>",
        "<span style=\"color:#000000;font-size:1.0em\"><b>URYVR</b></span>"
      ],
      "textposition": "middle center",
      "type": "scatter",
      "x": [
        -0.522381,
        0.183775,
        0.83827,
        0.942593,
        0.975317,
        -0.913748,
        -0.158495,
        -0.926835,
        -0.143902,
        -0.266525,
        0.653563,
        -0.61076,
        0.778875,
        0.942587,
        0.862642,
        -0.976436,
        0.571127,
        -0.270747,
        -0.673855,
        0.341685,
        -0.855681,
        0.328027,
        -0.801642,
        0.622389,
        0.815131,
        0.415029,
        -0.377741,
        -0.218255,
        0.080994,
        -0.374323,
        -0.773028,
        -0.072144,
        0.876156,
        0.106863,
        -0.624109,
        -0.81189,
        0.408808,
        0.977523,
        -0.84454,
        -0.69504,
        0.008275,
        0.404095,
        0.385726,
        -0.646827,
        0.49993,
        0.723258,
        0.570097,
        -0.473789,
        0.791285,
        -0.877232,
        -0.48886,
        0.813484,
        -0.914599,
        -0.89387,
        -0.338042,
        0.671673,
        0.176961,
        -0.361039,
        0.764309,
        -0.088465,
        0.657749,
        0.506442,
        -0.761366,
        -0.059212,
        0.774159,
        -0.802219,
        -0.674,
        0.220678,
        0.969424,
        -0.92158,
        -0.571473,
        0.623302,
        0.99874,
        0.296206,
        -0.957742,
        -0.814584,
        0.685934,
        0.810677,
        -0.772902,
        -0.930859,
        -0.793185,
        -0.019835,
        1.0
      ],
      "y": [
        0.699108,
        0.919261,
        -0.501021,
        0.30392,
        -0.341929,
        -0.16306,
        0.896827,
        0.199712,
        -0.981043,
        -0.98251,
        0.798106,
        -0.66464,
        0.762851,
        0.488658,
        0.416712,
        -0.010955,
        -0.717149,
        0.927766,
        0.891834,
        0.762961,
        -0.587328,
        -0.951362,
        -0.73519,
        0.496683,
        -0.026568,
        0.576914,
        -0.74847,
        -0.84112,
        0.898939,
        -0.928417,
        -0.60745,
        -0.914472,
        -0.21291,
        -0.955752,
        -0.868528,
        -0.437103,
        -0.857428,
        -0.147787,
        0.575939,
        -0.527077,
        -0.967725,
        0.914349,
        -0.740438,
        0.754862,
        0.931185,
        -0.561525,
        -0.53472,
        -0.868986,
        -0.410211,
        -0.356665,
        0.842036,
        0.654229,
        0.085463,
        -0.058716,
        0.735214,
        -0.697631,
        -0.847504,
        0.847846,
        0.238217,
        0.70713,
        0.059564,
        -0.876957,
        -0.236568,
        0.985429,
        -0.291158,
        0.176396,
        0.604654,
        -0.941761,
        -0.018306,
        0.409356,
        -0.772547,
        0.908972,
        0.095358,
        0.906183,
        0.283422,
        0.489171,
        -0.80944,
        0.567857,
        0.371652,
        -0.263321,
        0.707104,
        0.842704,
        0.228906
      ]
    }
  ],
  "layout": {
    "height": 800,
    "hovermode": "closest",
    "margin": {
      "b": 20,
      "l": 5,
      "r": 5,
      "t": 40
    },
    "showlegend": false,
    "template": {
      "data": {
        "bar": [
          {
            "error_x": {
              "color": "#2a3f5f"
            },
            "error_y": {
              "color": "#2a3f5f"
            },
            "marker": {
              "line": {
                "color": "white",
                "width": 0.5
              },
              "pattern": {
                "fillmode": "overlay",
                "size": 10,
                "solidity": 0.2
              }
            },
            "type": "bar"
          }
        ],
        "barpolar": [
          {
            "marker": {
              "line": {
                "color": "white",
                "width": 0.5
              },
              "pattern": {
                "fillmode": "overlay",
                "size": 10,
                "solidity": 0.2
              }
            },
            "type": "barpolar"
          }
        ],
        "carpet": [
          {
            "aaxis": {
              "endlinecolor": "#2a3f5f",
              "gridcolor": "#C8D4E3",
              "linecolor": "#C8D4E3",
              "minorgridcolor": "#C8D4E3",
              "startlinecolor": "#2a3f5f"
            },
            "baxis": {
              "endlinecolor": "#2a3f5f",
              "gridcolor": "#C8D4E3",
              "linecolor": "#C8D4E3",
              "minorgridcolor": "#C8D4E3",
              "startlinecolor": "#2a3f5f"
            },
            "type": "carpet"
          }
        ],
        "choropleth": [
          {
            "colorbar": {
              "outlinewidth": 0,
              "ticks": ""
            },
            "type": "choropleth"
          }
        ],
        "contour": [
          {
            "colorbar": {
              "outlinewidth": 0,
              "ticks": ""
            },
            "colorscale": [
              [
                0.0,
                "#0d0887"
              ],
              [
                0.1111111111111111,
                "#46039f"
              ],
              [
                0.2222222222222222,
                "#7201a8"
              ],
              [
                0.3333333333333333,
                "#9c179e"
              ],
              [
                0.4444444444444444,
                "#bd3786"
              ],
              [
                0.5555555555555556,
                "#d8576b"
              ],
              [
                0.6666666666666666,
                "#ed7953"
              ],
              [
                0.7777777777777778,
                "#fb9f3a"
              ],
              [
                0.8888888888888888,
                "#fdca26"
              ],
              [
                1.0,
                "#f0f921"
              ]
            ],
            "type": "contour"
          }
        ],
        "contourcarpet": [
          {
            "colorbar": {
              "outlinewidth": 0,
              "ticks": ""
            },
            "type": "contourcarpet"
          }
        ],
        "heatmap": [
          {
            "colorbar": {
              "outlinewidth": 0,
              "ticks": ""
            },
            "colorscale": [
              [
                0.0,
                "#0d0887"
              ],
              [
                0.1111111111111111,
                "#46039f"
              ],
              [
                0.2222222222222222,
                "#7201a8"
              ],
              [
                0.3333333333333333,
                "#9c179e"
              ],
              [
                0.4444444444444444,
                "#bd3786"
              ],
              [
                0.5555555555555556,
                "#d8576b"
              ],
              [
                0.6666666666666666,
                "#ed7953"
              ],
              [
                0.7777777777777778,
                "#fb9f3a"
              ],
              [
                0.8888888888888888,
                "#fdca26"
              ],
              [
                1.0,
                "#f0f921"
              ]
            ],
            "type": "heatmap"
          }
        ],
        "heatmapgl": [
          {
            "colorbar": {
              "outlinewidth": 0,
              "ticks": ""
            },
            "colorscale": [
              [
                0.0,
                "#0d0887"
              ],
              [
                0.1111111111111111,
                "#46039f"
              ],
              [
                0.2222222222222222,
                "#7201a8"
              ],
              [
                0.3333333333333333,
                "#9c179e"
              ],
              [
                0.4444444444444444,
                "#bd3786"
              ],
              [
                0.5555555555555556,
                "#d8576b"
              ],
              [
                0.6666666666666666,
                "#ed7953"
              ],
              [
                0.7777777777777778,
                "#fb9f3a"
              ],
              [
                0.8888888888888888,
                "#fdca26"
              ],
              [
                1.0,
                "#f0f921"
              ]
            ],
            "type": "heatmapgl"
          }
        ],
        "histogram": [
          {
            "marker": {
              "pattern": {
                "fillmode": "overlay",
                "size": 10,
                "solidity": 0.2
              }
            },
            "type": "histogram"
          }
        ],
        "histogram2d": [
          {
            "colorbar": {
              "outlinewidth": 0,
              "ticks": ""
            },
            "colorscale": [
              [
                0.0,
                "#0d0887"
              ],
              [
                0.1111111111111111,
                "#46039f"
              ],
              [
                0.2222222222222222,
                "#7201a8"
              ],
              [
                0.3333333333333333,
                "#9c179e"
              ],
              [
                0.4444444444444444,
                "#bd3786"
              ],
              [
                0.5555555555555556,
                "#d8576b"
              ],
              [
                0.6666666666666666,
                "#ed7953"
              ],
              [
                0.7777777777777778,
                "#fb9f3a"
              ],
              [
                0.8888888888888888,
                "#fdca26"
              ],
              [
                1.0,
                "#f0f921"
              ]
            ],
            "type": "histogram2d"
          }
        ],
        "histogram2dcontour": [
          {
            "colorbar": {
              "outlinewidth": 0,
              "ticks": ""
            },
            "colorscale": [
              [
                0.0,
                "#0d0887"
              ],
              [
                0.1111111111111111,
                "#46039f"
              ],
              [
                0.2222222222222222,
                "#7201a8"
              ],
              [
                0.3333333333333333,
                "#9c179e"
              ],
              [
                0.4444444444444444,
                "#bd3786"
              ],
              [
                0.5555555555555556,
                "#d8576b"
              ],
              [
                0.6666666666666666,
                "#ed7953"
              ],
              [
                0.7777777777777778,
                "#fb9f3a"
              ],
              [
                0.8888888888888888,
                "#fdca26"
              ],
              [
                1.0,
                "#f0f921"
              ]
            ],
            "type": "histogram2dcontour"
          }
        ],
        "mesh3d": [
          {
            "colorbar": {
              "outlinewidth": 0,
              "ticks": ""
            },
            "type": "mesh3d"
          }
        ],
        "parcoords": [
          {
            "line": {
              "colorbar": {
                "outlinewidth": 0,
                "ticks": ""
              }
            },
            "type": "parcoords"
          }
        ],
        "pie": [
          {
            "automargin": true,
            "type": "pie"
          }
        ],
        "scatter": [
          {
            "fillpattern": {
              "fillmode": "overlay",
              "size": 10,
              "solidity": 0.2
            },
            "type": "scatter"
          }
        ],
        "scatter3d": [
          {
            "line": {
              "colorbar": {
                "outlinewidth": 0,
                "ticks": ""
              }
            },
            "marker": {
              "colorbar": {
                "outlinewidth": 0,
                "ticks": ""
              }
            },
            "type": "scatter3d"
          }
        ],
        "scattercarpet": [
          {
            "marker": {
              "colorbar": {
                "outlinewidth": 0,
                "ticks": ""
              }
            },
            "type": "scattercarpet"
          }
        ],
        "scattergeo": [
          {
            "marker": {
              "colorbar": {
                "outlinewidth": 0,
                "ticks": ""
              }
            },
            "type": "scattergeo"
          }
        ],
        "scattergl": [
          {
            "marker": {
              "colorbar": {
                "outlinewidth": 0,
                "ticks": ""
              }
            },
            "type": "scattergl"
          }
        ],
        "scattermapbox": [
          {
            "marker": {
              "colorbar": {
                "outlinewidth": 0,
                "ticks": ""
              }
            },
            "type": "scattermapbox"
          }
        ],
        "scatterpolar": [
          {
            "marker": {
              "colorbar": {
                "outlinewidth": 0,
                "ticks": ""
              }
            },
            "type": "scatterpolar"
          }
        ],
        "scatterpolargl": [
          {
            "marker": {
              "colorbar": {
                "outlinewidth": 0,
                "ticks": ""
              }
            },
            "type": "scatterpolargl"
          }
        ],
        "scatterternary": [
          {
            "marker": {
              "colorbar": {
                "outlinewidth": 0,
                "ticks": ""
              }
            },
            "type": "scatterternary"
          }
        ],
        "surface": [
          {
            "colorbar": {
              "outlinewidth": 0,
              "ticks": ""
            },
            "colorscale": [
              [
                0.0,
                "#0d0887"
              ],
              [
                0.1111111111111111,
                "#46039f"
              ],
              [
                0.2222222222222222,
                "#7201a8"
              ],
              [
                0.3333333333333333,
                "#9c179e"
              ],
              [
                0.4444444444444444,
                "#bd3786"
              ],
              [
                0.5555555555555556,
                "#d8576b"
              ],
              [
                0.6666666666666666,
                "#ed7953"
              ],
              [
                0.7777777777777778,
                "#fb9f3a"
              ],
              [
                0.8888888888888888,
                "#fdca26"
              ],
              [
                1.0,
                "#f0f921"
              ]
            ],
            "type": "surface"
          }
        ],
        "table": [
          {
            "cells": {
              "fill": {
                "color": "#EBF0F8"
              },
              "line": {
                "color": "white"
              }
            },
            "header": {
              "fill": {
                "color": "#C8D4E3"
              },
              "line": {
                "color": "white"
              }
            },
            "type": "table"
          }
        ]
      },
      "layout": {
        "annotationdefaults": {
          "arrowcolor": "#2a3f5f",
          "arrowhead": 0,
          "arrowwidth": 1
        },
        "autotypenumbers": "strict",
        "coloraxis": {
          "colorbar": {
            "outlinewidth": 0,
            "ticks": ""
          }
        },
        "colorscale": {
          "diverging": [
            [
              0,
              "#8e0152"
            ],
            [
              0.1,
              "#c51b7d"
            ],
            [
              0.2,
              "#de77ae"
            ],
            [
              0.3,
              "#f1b6da"
            ],
            [
              0.4,
              "#fde0ef"
            ],
            [
              0.5,
              "#f7f7f7"
            ],
            [
              0.6,
              "#e6f5d0"
            ],
            [
              0.7,
              "#b8e186"
            ],
            [
              0.8,
              "#7fbc41"
            ],
            [
              0.9,
              "#4d9221"
            ],
            [
              1,
              "#276419"
            ]
          ],
          "sequential": [
            [
              0.0,
              "#0d0887"
            ],
            [
              0.1111111111111111,
              "#46039f"
            ],
            [
              0.2222222222222222,
              "#7201a8"
            ],
            [
              0.3333333333333333,
              "#9c179e"
            ],
            [
              0.4444444444444444,
              "#bd3786"
            ],
            [
              0.5555555555555556,
              "#d8576b"
            ],
            [
              0.6666666666666666,
              "#ed7953"
            ],
            [
              0.7777777777777778,
              "#fb9f3a"
            ],
            [
              0.8888888888888888,
              "#fdca26"
            ],
            [
              1.0,
              "#f0f921"
            ]
          ],
          "sequentialminus": [
            [
              0.0,
              "#0d0887"
            ],
            [
              0.1111111111111111,
              "#46039f"
            ],
            [
              0.2222222222222222,
              "#7201a8"
            ],
            [
              0.3333333333333333,
              "#9c179e"
            ],
            [
              0.4444444444444444,
              "#bd3786"
            ],
            [
              0.5555555555555556,
              "#d8576b"
            ],
            [
              0.6666666666666666,
              "#ed7953"
            ],
            [
              0.7777777777777778,
              "#fb9f3a"
            ],
            [
              0.8888888888888888,
              "#fdca26"
            ],
            [
              1.0,
              "#f0f921"
            ]
          ]
        },
        "colorway": [
          "#636efa",
          "#EF553B",
          "#00cc96",
          "#ab63fa",
          "#FFA15A",
          "#19d3f3",
          "#FF6692",
          "#B6E880",
          "#FF97FF",
          "#FECB52"
        ],
        "font": {
          "color": "#2a3f5f"
        },
        "geo": {
          "bgcolor": "white",
          "lakecolor": "white",
          "landcolor": "white",
          "showlakes": true,
          "showland": true,
          "subunitcolor": "#C8D4E3"
        },
        "hoverlabel": {
          "align": "left"
        },
        "hovermode": "closest",
        "mapbox": {
          "style": "light"
        },
        "paper_bgcolor": "white",
        "plot_bgcolor": "white",
        "polar": {
          "angularaxis": {
            "gridcolor": "#EBF0F8",
            "linecolor": "#EBF0F8",
            "ticks": ""
          },
          "bgcolor": "white",
          "radialaxis": {
            "gridcolor": "#EBF0F8",
            "linecolor": "#EBF0F8",
            "ticks": ""
          }
        },
        "scene": {
          "xaxis": {
            "backgroundcolor": "white",
            "gridcolor": "#DFE8F3",
            "gridwidth": 2,
            "linecolor": "#EBF0F8",
            "showbackground": true,
            "ticks": "",
            "zerolinecolor": "#EBF0F8"
          },
          "yaxis": {
            "backgroundcolor": "white",
            "gridcolor": "#DFE8F3",
            "gridwidth": 2,
            "linecolor": "#EBF0F8",
            "showbackground": true,
            "ticks": "",
            "zerolinecolor": "#EBF0F8"
          },
          "zaxis": {
            "backgroundcolor": "white",
            "gridcolor": "#DFE8F3",
            "gridwidth": 2,
            "linecolor": "#EBF0F8",
            "showbackground": true,
            "ticks": "",
            "zerolinecolor": "#EBF0F8"
          }
        },
        "shapedefaults": {
          "line": {
            "color": "#2a3f5f"
          }
        },
        "ternary": {
          "aaxis": {
            "gridcolor": "#DFE8F3",
            "linecolor": "#A2B1C6",
            "ticks": ""
          },
          "baxis": {
            "gridcolor": "#DFE8F3",
            "linecolor": "#A2B1C6",
            "ticks": ""
          },
          "bgcolor": "white",
          "caxis": {
            "gridcolor": "#DFE8F3",
            "linecolor": "#A2B1C6",
            "ticks": ""
          }
        },
        "title": {
          "x": 0.05
        },
        "xaxis": {
          "automargin": true,
          "gridcolor": "#EBF0F8",
          "linecolor": "#EBF0F8",
          "ticks": "",
          "title": {
            "standoff": 15
          },
          "zerolinecolor": "#EBF0F8",
          "zerolinewidth": 2
        },
        "yaxis": {
          "automargin": true,
          "gridcolor": "#EBF0F8",
          "linecolor": "#EBF0F8",
          "ticks": "",
          "title": {
            "standoff": 15
          },
          "zerolinecolor": "#EBF0F8",
          "zerolinewidth": 2
        }
      }
    },
    "width": 800,
    "xaxis": {
      "showgrid": false,
      "visible": false,
      "zeroline": false
    },
    "yaxis": {
      "scaleanchor": "x",
      "scaleratio": 1,
      "showgrid": false,
      "visible": false,
      "zeroline": false
    }
  }
}